Workbook

Sheet GUIA
A1: BASE DE DATOS DEL DASHBOARD | B1: BD_dashboard_operaciones_github.xlsx
A2: Cómo usarla | B2: Edita únicamente las hojas de datos. El HTML toma la información de este archivo.
A3: Fechas de corte | B3: Cámbialas en CONFIG_HTML / CONFIG_DASHBOARD. Ej.: 22/09/2026.
A4: Nombres de columnas | B4: Puedes cambiar los nombres visibles en CONFIG_HTML o en la columna DISPLAY_NAME de ENCABEZADOS.
A5: Resumen Ejecutivo | B5: No se edita manualmente: el HTML lo calcula a partir de las demás hojas.
A6: Iniciativas Estratégicas | B6: Edita BD_INICIATIVAS. La pestaña Resumen reproduce la lógica de TD por estado y FECHA FIN PLANIFICADA.
A7: Estados permitidos | B7: EJECUTADO, EN PROCESO, PENDIENTE, CANCELADO.
A8: Campus | B8: Edita la lista en LISTAS si agregas o renombras campus.
A9: Importante | B9: No cambies los nombres de las hojas técnicas si quieres mantener la vinculación actual del HTML.
A10: MEJORAS_PROGRAMACION | B10: Tabla auxiliar para compatibilidad con el HTML; se genera a partir de BD_INICIATIVAS.

Sheet CONFIG_HTML
A1: selector | B1: tipo | C1: atributo | D1: valor | E1: descripcion
A2: meta:sec-resumen:eyebrow | B2: text | D2: Proyectos operacionales | E2: Etiqueta superior del Resumen Ejecutivo
A3: meta:sec-resumen:title | B3: text | D3: Resumen ejecutivo | E3: Título del Resumen Ejecutivo
A4: #sec-limpieza-cobertura .section-intro p | B4: text | D4: Vista consolidada por campus · Dotación agosto 2026 vs. cobertura 17/09 | E4: Texto de corte/introducción
A5: #sec-limpieza-presupuesto .section-intro p | B5: text | D5: Presupuesto 2026 y descuentos / penalidades registrados | E5: Texto de introducción
A6: #sec-operaciones-aula911 .section-intro p | B6: text | D6: Indicadores 2026 · corte 22/09 | E6: Fecha de corte Aula 911
A7: #sec-operaciones-rondas .section-intro p | B7: text | D7: Indicadores 2026 · corte 23/09 | E7: Fecha de corte Rondas
A8: #sec-proyectos-resumen .section-intro p | B8: text | D8: Portafolio consolidado y avance de obra / compras | E8: Texto de introducción
A9: #sec-mejoras-resumen .section-intro p | B9: text | D9: Consolidado por estado y programación mensual | E9: Texto de introducción
A10: #sec-listo-resumen .section-intro p | B10: text | D10: Estado de diseño, obra y operación por campus | E10: Texto de introducción

Sheet ENCABEZADOS
A1: hoja | B1: campo | C1: display_name | D1: orden | E1: visible | F1: formato
A2: LIMPIEZA_COBERTURA | B2: col_1 | C2: Zona | D2: 1 | E2: Sí
A3: LIMPIEZA_COBERTURA | B3: col_2 | C3: Campus | D3: 2 | E3: Sí
A4: LIMPIEZA_COBERTURA | B4: col_3 | C4: Turno Mañana | D4: 3 | E4: Sí
A5: LIMPIEZA_COBERTURA | B5: col_4 | C5: Turno Tarde | D5: 4 | E5: Sí
A6: LIMPIEZA_COBERTURA | B6: col_5 | C6: Turno Noche | D6: 5 | E6: Sí
A7: LIMPIEZA_COBERTURA | B7: col_6 | C7: Cobertura Mañana | D7: 6 | E7: Sí
A8: LIMPIEZA_COBERTURA | B8: col_7 | C8: Cobertura Tarde | D8: 7 | E8: Sí
A9: LIMPIEZA_COBERTURA | B9: col_8 | C9: Cobertura Noche | D9: 8 | E9: Sí
A10: LIMPIEZA_COBERTURA | B10: col_9 | C10: Pendiente Mañana | D10: 9 | E10: Sí
A11: LIMPIEZA_COBERTURA | B11: col_10 | C11: Pendiente Tarde | D11: 10 | E11: Sí
A12: LIMPIEZA_COBERTURA | B12: col_11 | C12: Pendiente Noche | D12: 11 | E12: Sí
A13: LIMPIEZA_COBERTURA | B13: col_12 | C13: # | D13: 12 | E13: Sí
... A54: LISTO | B54: col_7 | C54: Nueva fecha | D54: 7 | E54: Sí
A55: MEJORAS_PROGRAMACION | B55: col_1 | C55: CAMPUS | D55: 1 | E55: Sí | F55: texto
A56: MEJORAS_PROGRAMACION | B56: col_2 | C56: Fecha inicio | D56: 2 | E56: No | F56: fecha
A57: MEJORAS_PROGRAMACION | B57: col_3 | C57: Fecha fin | D57: 3 | E57: No | F57: fecha
A58: MEJORAS_PROGRAMACION | B58: col_4 | C58: <1/03/2026 | D58: 4 | E58: Sí | F58: entero
A59: MEJORAS_PROGRAMACION | B59: col_5 | C59: Mar | D59: 5 | E59: Sí | F59: entero
A60: MEJORAS_PROGRAMACION | B60: col_6 | C60: Abr | D60: 6 | E60: Sí | F60: entero
A61: MEJORAS_PROGRAMACION | B61: col_7 | C61: May | D61: 7 | E61: Sí | F61: entero
A62: MEJORAS_PROGRAMACION | B62: col_8 | C62: Jun | D62: 8 | E62: Sí | F62: entero
A63: MEJORAS_PROGRAMACION | B63: col_9 | C63: Jul | D63: 9 | E63: Sí | F63: entero
A64: MEJORAS_PROGRAMACION | B64: col_10 | C64: Ago | D64: 10 | E64: Sí | F64: entero
A65: MEJORAS_PROGRAMACION | B65: col_11 | C65: Set | D65: 11 | E65: Sí | F65: entero
A66: MEJORAS_PROGRAMACION | B66: col_12 | C66: Oct | D66: 12 | E66: Sí | F66: entero
... A69: MEJORAS_PROGRAMACION | B69: col_15 | C69: Total general | D69: 15 | E69: Sí | F69: entero

Sheet CONFIG_DASHBOARD
A1: clave | B1: valor | C1: descripcion
A2: archivo_excel | B2: BD_dashboard_operaciones_github.xlsx | C2: Nombre del archivo que debe leer el HTML
A3: anio | B3: 2026 | C3: Año de trabajo
A4: iniciativas_fecha_corte | B4: 01/03/2026 | C4: Fecha usada para la columna <1/03/2026
A5: aula911_fecha_corte | B5: 22/09/2026 | C5: Fecha de corte mostrada en Aula 911
A6: rondas_fecha_corte | B6: 23/09/2026 | C6: Fecha de corte mostrada en Rondas
A7: limpieza_cobertura_fecha_corte | B7: 17/09/2026 | C7: Fecha de cobertura
A8: limpieza_presupuesto_corte | B8: 30/09/2026 | C8: Corte del presupuesto/penalidades

Sheet KPIs_HTML
A1: modulo | B1: indicador | C1: valor | D1: unidad | E1: descripcion
A2: Limpieza | B2: Cobertura total | C2: 0.95 | D2: porcentaje | E2: Cobertura total
A3: Limpieza | B3: Cobertura semanal total | C3: 0.95 | D3: porcentaje | E3: Alias compatible con HTML
A4: Limpieza | B4: Dotación programada (turnos) | C4: 616 | D4: entero | E4: Turnos programados
A5: Limpieza | B5: Turnos cubiertos | C5: 584 | D5: entero | E5: Turnos cubiertos
A6: Limpieza | B6: Turnos pendientes | C6: 32 | D6: entero | E6: Turnos pendientes
A7: Limpieza | B7: Presupuesto 2026 | C7: 18000000 | D7: moneda | E7: Presupuesto
A8: Limpieza | B8: Presupuesto ejecutado | C8: 11200000 | D8: moneda | E8: Ejecutado
A9: Limpieza | B9: Nivel de ejecución | C9: 0.622 | D9: porcentaje | E9: Ejecutado / presupuesto
A10: Limpieza | B10: Descuentos + penalidades | C10: 222439 | D10: moneda | E10: Total
A11: Aula 911 | B11: # incidencias | C11: 23261 | D11: entero | E11: Incidencias
A12: Aula 911 | B12: Tiempo acepta solicitud | C12: 4.7 | D12: minutos | E12: Minutos
A13: Aula 911 | B13: Tiempo atiende solicitud | C13: 4.7 | D13: minutos | E13: Minutos
... A27: Listo | B27: Por implementar | C27: 7 | D27: entero | E27: Por implementar

Sheet LIMPIEZA_COBERTURA
A1: zona | B1: campus | C1: dot_m | D1: dot_t | E1: dot_n | F1: cob_m | G1: cob_t | H1: cob_n | I1: pend_m | J1: pend_t | K1: pend_n | L1: pend_total | M1: cobertura_pct
A2: LIMA | B2: SJL I | C2: 9 | D2: 8 | E2: 0 | F2: 9 | G2: 8 | H2: 0 | I2: 0 | J2: 0 | K2: 0 | L2: 0 | M2: 100
A3: LIMA | B3: ALMACEN CENTRAL | C3: 1 | D3: 0 | E3: 0 | F3: 1 | G3: 0 | H3: 0 | I3: 0 | J3: 0 | K3: 0 | L3: 0 | M3: 100
A4: LIMA | B4: JARRITA | C4: 3 | D4: 2 | E4: 0 | F4: 3 | G4: 2 | H4: 0 | I4: 0 | J4: 0 | K4: 0 | L4: 0 | M4: 100
A5: LIMA | B5: TORRE NUEVA | C5: 15 | D5: 15 | E5: 8 | F5: 15 | G5: 15 | H5: 8 | I5: 0 | J5: 0 | K5: 0 | L5: 0 | M5: 100
A6: LIMA | B6: LIMA NORTE | C6: 19 | D6: 19 | E6: 12 | F6: 19 | G6: 19 | H6: 12 | I6: 0 | J6: 0 | K6: 0 | L6: 0 | M6: 100
A7: PROVINCIA | B7: AREQUIPA POSTGRADO | C7: 1 | D7: 2 | E7: 0 | F7: 1 | G7: 2 | H7: 0 | I7: 0 | J7: 0 | K7: 0 | L7: 0 | M7: 100
A8: PROVINCIA | B8: CHIMBOTE | C8: 16 | D8: 10 | E8: 0 | F8: 16 | G8: 10 | H8: 0 | I8: 0 | J8: 0 | K8: 0 | L8: 0 | M8: 100
A9: PROVINCIA | B9: PIURA | C9: 15 | D9: 15 | E9: 8 | F9: 15 | G9: 15 | H9: 8 | I9: 0 | J9: 0 | K9: 0 | L9: 0 | M9: 100
A10: PROVINCIA | B10: TRUJILLO | C10: 8 | D10: 7 | E10: 0 | F10: 8 | G10: 7 | H10: 0 | I10: 0 | J10: 0 | K10: 0 | L10: 0 | M10: 100
A11: PROVINCIA | B11: HUANCAYO | C11: 13 | D11: 8 | E11: 0 | F11: 13 | G11: 8 | H11: 0 | I11: 0 | J11: 0 | K11: 0 | L11: 0 | M11: 100
A12: PROVINCIA | B12: HUANUCO | C12: 1 | D12: 0 | E12: 0 | F12: 1 | G12: 0 | H12: 0 | I12: 0 | J12: 0 | K12: 0 | L12: 0 | M12: 100
A13: PROVINCIA | B13: IQUITOS | C13: 9 | D13: 9 | E13: 0 | F13: 9 | G13: 9 | H13: 0 | I13: 0 | J13: 0 | K13: 0 | L13: 0 | M13: 100
... A29: LIMA | B29: JOSE DIAZ | C29: 4 | D29: 4 | E29: 0 | F29: 3 | G29: 3 | H29: 0 | I29: 1 | J29: 1 | K29: 0 | L29: 2 | M29: 75

Sheet LIMPIEZA_PRESUPUESTO
A1: concepto | B1: periodo | C1: monto
A2: Descuentos faltas/tardanzas | B2: 2026-05 | C2: 45862
A3: Descuentos faltas/tardanzas | B3: 2026-06 | C3: 37330
A4: Descuentos faltas/tardanzas | B4: 2026-07 | C4: 33645
A5: Descuentos faltas/tardanzas | B5: 2026-08 | C5: 33266
A6: Descuentos faltas/tardanzas | B6: 2026-09 | C6: 57771
A7: Penalidades | B7: 2026-05 | C7: 2507
A8: Penalidades | B8: 2026-06 | C8: 3902
A9: Penalidades | B9: 2026-07 | C9: 493
A10: Penalidades | B10: 2026-08 | C10: 583
A11: Penalidades | B11: 2026-09 | C11: 7080

Sheet AULA911_CAMPUS
A1: campus | B1: tiempo_acepta_min | C1: tiempo_atiende_min | D1: tiempo_total_min | E1: valoracion | F1: es_subsede
A2: CAMPUS CHIMBOTE | B2: 1.86 | C2: 2.95 | D2: 4.9 | E2: 4.7 | F2: 0
A3: CAMPUS TRUJILLO | B3: 1.98 | C3: 3.4 | D3: 5.4 | E3: 5 | F3: 0
A4: CAMPUS PIURA | B4: 2.54 | C4: 4.1 | D4: 6.6 | E4: 4.8 | F4: 0
A5: CAMPUS AREQUIPA | B5: 2.17 | C5: 4.07 | D5: 6.9 | E5: 4.8 | F5: 0
A6: Tacna y Arica | B6: 1.94 | C6: 4.34 | D6: 6.3 | E6: 4.8 | F6: 1
A7: Parra | B7: 3.14 | C7: 3.64 | D7: 6.8 | E7: 4.8 | F7: 1
A8: Parra 2 | B8: 3.22 | C8: 4.53 | D8: 7.7 | E8: 4.6 | F8: 1
A9: CAMPUS IQUITOS | B9: 2.59 | C9: 4.38 | D9: 7 | E9: 4.8 | F9: 0
A10: CAMPUS HUANCAYO | B10: 2.8 | C10: 4.34 | D10: 7.1 | F10: 0
A11: CAMPUS ATE UTP | B11: 1.7 | C11: 5.81 | D11: 7.4 | E11: 4.8 | F11: 0
A12: CAMPUS CHICLAYO | B12: 4.16 | C12: 3.54 | D12: 7.7 | E12: 4.6 | F12: 0
A13: CAMPUS SAN JUAN DE LURIGANCHO | B13: 4.15 | C13: 3.48 | D13: 7.7 | E13: 4.4 | F13: 0
A14: CAMPUS ICA | B14: 5.53 | C14: 2.79 | D14: 8.2 | E14: 3.2 | F14: 0
A15: CAMPUS LIMA | B15: 4.13 | C15: 4.17 | D15: 8.3 | E15: 3.8 | F15: 0
A16: Torre Petit Thouars | B16: 1.94 | C16: 2.63 | D16: 4.6 | E16: 3.4 | F16: 1
A17: Edificio Pacífico | B17: 2.27 | C17: 3.76 | D17: 6 | E17: 4.4 | F17: 1
A18: Torre Arequipa | B18: 4.31 | C18: 4.06 | D18: 8.4 | F18: 1
A19: Sede Central | B19: 7.85 | C19: 6.7 | D19: 14.5 | E19: 3.4 | F19: 1
A20: CAMPUS PUCALLPA | B20: 7.01 | C20: 2.19 | D20: 9.3 | E20: 4.8 | F20: 0
A21: CAMPUS TACNA | B21: 3.67 | C21: 6.13 | D21: 9.8 | E21: 5 | F21: 0
A22: CAMPUS LIMA NORTE UTP | B22: 9.03 | C22: 7.46 | D22: 16.6 | E22: 4.2 | F22: 0
A23: CAMPUS LIMA SUR UTP | B23: 10.28 | C23: 7.28 | D23: 17.5 | E23: 4.4 | F23: 0

Sheet AULA911_TOP
A1: tipo_incidencia | B1: participacion
A2: Problema con la PC | B2: 29
A3: Problema con el proyector | B3: 28
A4: Problema con el audio | B4: 13
A5: Problema con el Zoom | B5: 13
A6: Ambiente cerrado | B6: 17

Sheet RONDAS
A1: sede | B1: dispositivos_asignados | C1: responsables | D1: programado | E1: ejecutado | F1: cumplimiento_pct | G1: es_subsede
A2: 05. UTP Lima Sur | B2: 20 | C2: 16 | D2: 2464 | E2: 2753 | F2: 95 | G2: 0
A3: 04. UTP Ate | B3: 22 | C3: 12 | D3: 4638 | E3: 6058 | F3: 94 | G3: 0
A4: 03. UTP SJL | B4: 24 | C4: 9 | D4: 5057 | E4: 6152 | F4: 92 | G4: 0
A5: 11. UTP Huancayo | B5: 16 | C5: 7 | D5: 5026 | E5: 4575 | F5: 89 | G5: 0
A6: 07. UTP Chiclayo | B6: 53 | C6: 16 | D6: 10504 | E6: 11064 | F6: 83 | G6: 0
A7: 01. UTP Lima Centro | B7: 90 | C7: 33 | D7: 14434 | E7: 15220 | F7: 82 | G7: 0
A8: 03. UTP Lima Centro Torre Petit Thouars | B8: 19 | C8: 7 | D8: 5418 | E8: 5287 | F8: 97 | G8: 1
A9: 01. UTP Lima Centro Sede Central | B9: 36 | C9: 9 | D9: 1930 | E9: 1884 | F9: 84 | G9: 1
A10: 04. UTP Lima Centro Torre Pacífico | B10: 13 | C10: 7 | D10: 3812 | E10: 3147 | F10: 82 | G10: 1
A11: 02. UTP Lima Centro Torre Arequipa | B11: 22 | C11: 12 | D11: 3274 | E11: 4902 | F11: 59 | G11: 1
A12: 06. UTP Arequipa | B12: 65 | C12: 23 | D12: 14327 | E12: 14839 | F12: 80 | G12: 0
A13: 02. UTP Arequipa Parra I | B13: 22 | C13: 9 | D13: 4469 | E13: 4938 | F13: 88 | G13: 1
... A23: 15. UTP Tacna | B23: 66 | C23: 6 | D23: 12426 | E23: 2643 | F23: 20 | G23: 0

Sheet PROYECTOS
A1: proyecto | B1: estado | C1: avance_obra_pct | D1: avance_compras_pct | E1: fecha_objetivo_texto | F1: con_observaciones | G1: nueva_fecha_texto
A2: Nuevo Edificio Campus Lima Norte (Salud) – Por definir ITSE | B2: En proceso | C2: 98 | D2: 100 | E2: AGO 26 | F2: - | G2: -
A3: Laboratorios Salud Campus Lima Norte – ETAPA I – Pendiente ITSE | B3: En proceso | C3: 100 | D3: 100 | E3: OCT 26 | F3: - | G3: -
A4: Laboratorios de Técnicas Dietéticas y Terapia (Iquitos –Pucallpa) | B4: En proceso | C4: 100 | D4: 90 | E4: SET 26 | F4: - | G4: -
A5: Nuevo Campus Huánuco - SUNEDU - 12/10 | B5: En proceso | C5: 99 | D5: 100 | E5: OCT 26 | F5: - | G5: -
A6: Nuevo Campus Huamanga – SUNEDU 29/10 | B6: En proceso | C6: 98 | D6: 100 | E6: OCT 26 | F6: - | G6: -
A7: Nuevo Campus Juliaca – ITSE - 18/11 | B7: En proceso | C7: 87 | D7: 92.5 | E7: NOV 26 | F7: - | G7: -
A8: Nuevos Laboratorios de Hotelería y Turismo – Lima Centro - ITSE 09/12 | B8: En proceso | C8: 51 | D8: 0 | E8: ENE 27 | F8: - | G8: -
A9: Nuevos Laboratorios de Odontología – Lima Centro - Jarrita | B9: En proceso | C9: 15 | D9: 0 | E9: MAR 27 | F9: - | G9: -
A10: Nuevo Campus Cusco | B10: Pendiente | C10: 0 | D10: 0 | E10: JUL 27 | F10: - | G10: -
A11: Ampliación Campus Huancayo | B11: Pendiente | C11: 0 | D11: 0 | E11: AGO 27 | F11: - | G11: -
A12: Ampliación Campus Piura | B12: Pendiente | C12: 0 | D12: 0 | E12: AGO 27 | F12: - | G12: -
A13: Remodelación de Saco Oliveros | B13: En proceso | C13: 0 | D13: 0 | E13: DIC 15 | F13: - | G13: -
... A20: Medicina Piura | B20: Pendiente | C20: 0 | D20: 0 | E20: MAR 27 | F20: - | G20: -

Sheet PROYECTO_DETALLE
A1: campus | B1: descripcion | C1: avance_obra_pct | D1: avance_compras_pct | E1: avance_implementacion_pct | F1: fecha_objetivo_texto | G1: url_seguimiento
A2: Campus Huánuco | B2: 1 semisótano · 5 pisos · 1 azotea | C2: 99 | D2: 100 | E2: 95 | F2: OCT 26 | G2: https://seguimiento-proyectos-ops-utp.proyectos-ops-utp.workers.dev/?p=implementacion-nueva-sede-utp-huanuco-etapa-1&tab=p1
A3: Campus Huamanga | B3: 1 sótano · 5 pisos · 1 azotea | C3: 98 | D3: 100 | E3: 91 | F3: OCT 26 | G3: https://seguimiento-proyectos-ops-utp.proyectos-ops-utp.workers.dev/?p=implementacion-nueva-sede-utp-huamanga-etapa-1&tab=p1
A4: Campus Juliaca | B4: 1 sótano · 5 pisos · 1 azotea | C4: 87 | D4: 92.5 | E4: 35.5 | F4: NOV 26 | G4: https://seguimiento-proyectos-ops-utp.proyectos-ops-utp.workers.dev/?p=implementacion-nueva-sede-utp-juliaca-etapa-1&tab=p1
A5: Campus Lima Norte | B5: 4 sótanos · 1 semisótano · 7 pisos · 1 azotea | C5: 98 | D5: 95 | E5: 96.5 | F5: SET 26 | G5: https://seguimiento-proyectos-ops-utp.proyectos-ops-utp.workers.dev/?p=implementacion-nueva-torre-utp-lima-norte&tab=p1
A6: Proyecto Saco Olivero | B6: 1 semisótano · 9 pisos · 1 azotea | C6: 0 | D6: 0 | E6: 0 | F6: DIC 15 | G6: https://seguimiento-proyectos-ops-utp.proyectos-ops-utp.workers.dev/?p=implementacion-nueva-torre-utp-lima-norte&tab=p1

Sheet IMPLEMENTACIONES
A1: titulo | B1: avance_pct | C1: url
A2: Trujillo | ÁREAS DE ESPARCIMIENTO | B2: 64 | C2: https://lovely-horn-db6.notion.site/3d755146449f80c0a3cce29f4f317a51?v=3d755146449f802ba9a4000c451a72db
A3: Trujillo | ZONA DE FOTOCOPIADO | B3: 75 | C3: https://lovely-horn-db6.notion.site/3d755146449f80c0a3cce29f4f317a51?v=3d755146449f802ba9a4000c451a72db
A4: Trujillo | CAFETERÍA CONCESIONARIO | B4: 82 | C4: https://lovely-horn-db6.notion.site/3d755146449f80c0a3cce29f4f317a51?v=3d755146449f802ba9a4000c451a72db
A5: Trujillo | CAFETERÍA CAMPUS | B5: 83 | C5: https://lovely-horn-db6.notion.site/3d755146449f80c0a3cce29f4f317a51?v=3d755146449f802ba9a4000c451a72db
A6: SJL | ÁREAS DE ESPARCIMIENTO | B6: 33 | C6: https://lovely-horn-db6.notion.site/3d755146449f80c0a3cce29f4f317a51?v=3d755146449f802ba9a4000c451a72db
A7: SJL | ZONA DE FOTOCOPIADO | B7: 75 | C7: https://lovely-horn-db6.notion.site/3d755146449f80c0a3cce29f4f317a51?v=3d755146449f802ba9a4000c451a72db
A8: SJL | CAFETERÍA CONCESIONARIO | B8: 91 | C8: https://lovely-horn-db6.notion.site/3d755146449f80c0a3cce29f4f317a51?v=3d755146449f802ba9a4000c451a72db
A9: Piura | ÁREAS DE ESPARCIMIENTO | B9: 42 | C9: https://lovely-horn-db6.notion.site/3d755146449f80c0a3cce29f4f317a51?v=3d755146449f802ba9a4000c451a72db
A10: Piura | ZONA DE FOTOCOPIADO | B10: 100 | C10: https://lovely-horn-db6.notion.site/3d755146449f80c0a3cce29f4f317a51?v=3d755146449f802ba9a4000c451a72db
A11: Piura | CAFETERÍA CONCESIONARIO | B11: 64 | C11: https://lovely-horn-db6.notion.site/3d755146449f80c0a3cce29f4f317a51?v=3d755146449f802ba9a4000c451a72db
A12: Lima Sur | ÁREAS DE ESPARCIMIENTO | B12: 100 | C12: https://lovely-horn-db6.notion.site/3d755146449f80c0a3cce29f4f317a51?v=3d755146449f802ba9a4000c451a72db
... A55: Arequipa Parra 2 | CAFETERÍA CONCESIONARIO | B55: 82 | C55: https://lovely-horn-db6.notion.site/3d755146449f80c0a3cce29f4f317a51?v=3d755146449f802ba9a4000c451a72db

Sheet LISTO
A1: campus | B1: diseno_pct | C1: obra_pct | D1: operacion | E1: fecha_objetivo_texto | F1: con_observacion | G1: nueva_fecha_texto
A2: LC – Torre Tecnológica Arequipa (I) | B2: 100 | C2: 100 | D2: Sí | E2: Mar-26 | F2: No | G2: -
A3: LC – Sede Central (I) | B3: 100 | C3: 100 | D3: Sí | E3: Mar-26 | F3: Sí | G3: 6/04/2026
A4: LC – Torre II (I) | B4: 100 | C4: 100 | D4: Sí | E4: Mar-26 | F4: No | G4: -
A5: LS – Piso 1 (I) | B5: 100 | C5: 100 | D5: Sí | E5: Mar-26 | F5: No | G5: -
A6: LS – Piso 10 (I) | B6: 100 | C6: 100 | D6: Sí | E6: Mar-26 | F6: No | G6: -
A7: Ica (I) | B7: 100 | C7: 100 | D7: Sí | E7: Mar-26 | F7: No | G7: -
A8: Arequipa – Tacna y Arica (I) | B8: 100 | C8: 100 | D8: Sí | E8: Mar-26 | F8: No | G8: -
A9: LC – Pacífico (II) | B9: 100 | C9: 100 | D9: Sí | E9: Mar-26 | F9: Sí | G9: 13/04/2026
A10: SJL (II) | B10: 100 | C10: 100 | D10: Sí | E10: Mar-26 | F10: Sí | G10: 30/03/2026
A11: Arequipa – Parra 2 (II) | B11: 100 | C11: 100 | D11: Sí | E11: Mar-26 | F11: Sí | G11: 30/03/2026
A12: Trujillo (II) | B12: 100 | C12: 100 | D12: Sí | E12: Jun-26 | F12: No | G12: -
A13: Lima Norte (II) – Pendiente | B13: 100 | C13: 0 | D13: - | E13: - | F13: - | G13: -
A14: Chiclayo (II) | B14: 100 | C14: 0 | D14: - | E14: Oct-26 | F14: - | G14: -
A15: ATE (II) | B15: 100 | C15: 40 | D15: - | E15: Oct-26
A16: Pucallpa (III) | B16: 100 | C16: 0 | D16: - | E16: Nov-26 | F16: - | G16: -
A17: Iquitos (III) | B17: 90 | C17: 0 | D17: - | E17: Nov-26 | F17: - | G17: -
A18: Chimbote (III) | B18: 100 | C18: 0 | D18: - | E18: Nov-26 | F18: - | G18: -
A19: Resto de campus (IV) | B19: 0 | C19: 0 | D19: - | E19: - | F19: - | G19: -

Sheet BD_INICIATIVAS
B1: 5518026 | C1: PPTO OPS | D1: =+SUM(U7:U107) -> 5454483.2 | F1: =B1-D1 -> 63542.8
B2: 3192205 | C2: PPTO SSGG | D2: =+SUM(U108:U300) -> 3372510 | F2: =B2-D2 -> -180305.03 | R2: 8710231 | T2: 106806.94
B3: 8710231 | C3: TOTAL PPTO | D3: =+D1+D2 -> 8826993.2 | F3: =B3-D3 -> -116762.23
C4: TOTAL EJECUTADO | D4: =+SUM(V7:V300) -> 3312644.6 | R4: =R2-D3 -> -116762.23 | T4: =R2+T2 -> 8817037.9
A6: # | B6: ID | C6: ORIGEN2 | D6: RESPONSABLE DEL PROYECTO | E6: RESPONSABLE DEL PROYECTO2 | F6: CORREO | G6: TELÉFONO | H6: Columna1 | I6: BREVE DESCRIPCIÓN DEL PROYECTO | J6: LINK VIDEO / FOTOS | K6: ESTADO INICAL DE APROBACIÓN | L6: PUNTAJE PRIORIDAD | M6: IMPACTO SERVICIO AL ALUMNO | N6: IMPACTO IMAGEN / REPUTACIÓN | O6: IMPACTO EN OPERACIÓN | P6: COMENTARIOS DE INFRAESTRUCTURA | Q6: TIENE PRESUPUESTO | R6: CAMPUS | S6: UE | T6: UBICACIÓN PROYECTO (UE) | U6: MONTO INVERSIÓN DEL PROYECTO (INC IGV) | V6: MONTO EJECUTADO DEL PROYECTO (INC IGV) | W6: PRIORIDAD | X6: FECHA INICIO PLANIFICADA | Y6: FECHA FIN PLANIFICADA | Z6: FECHA INICIO REAL | AA6: FECHA FIN REAL | AB6: ESTADO PROYECTO OPERATIVO | AC6: ESTADO PROYECTO FINANCIERO | AD6: EJECUTOR | AE6: SC | AF6: FECHA INGRESO SC | AG6: OC | AH6: FECHA GENERACIÓN OC | AI6: CÓDIGO | AJ6: DESCRIPCIÓN PROYECTO | AK6: FECHA ATENCIÓN | AL6: ATENDIDO POR | AM6: Comentario | AN6: EFICIENCIA | AO6: Comentarios Eloy | AP6: Caso
A7: 1 | B7: OPS_001 | C7: OPS | D7: Nestor Silva | H7: ACONDICIONAR AMBIENTE AL COSTADO DE TOPICO EN TORREB PARA QUE SEA KITCHENET DOCENTE | I7: TORRE B NO TIENE ESPACIOS PARA DOCENTES (CAD KITCHENET), UTILIZAR EL ESPACIO DE LA OFICINA CONTIGUA AL TÓPICOQUE SE ENCUENTRA VACÍA COMO KITCHENNETTE PARA DOCENTES | J7: https://www,dropbox,com/scl/fo/t8a94dgffyjikmjdnamuh/ADI5WDjY4ELz_kWRkOXgTm8?rlkey=dtm5fyuuwarbzrhs4wqefssqt&dl=0 | K7: OK | L7: =SUM(M7:O7) -> 9 | M7: 1 | N7: 5 | O7: 3 | P7: OK para evaluar | Q7: SI | R7: UTP SJL | S7: 10220110 | T7: UTP AV,SOL SUB LT 13B MZG SJL - LIMA | U7: 25000 | V7: 25000 | W7: B | X7: 46235 | Y7: 46264 | AB7: EJECUTADO | AD7: Infraestructura | AI7: PROY1430 | AM7: Consultar con Infraestructura
A8: 2 | B8: OPS_002 | C8: OPS | D8: VICENTE CAYETANO RODRIGUEZ PASTOR | F8: vrodriguep@utp,edu,pe | G8: 955 141 444 | H8: Ampliación de la oficina de TI | I8: Necesidad de ampliar la oficina de Sistemas (TI) por la cantidad de colaboradores que allí laboran, Además el ambiente requiere contar con un área adecuada para el almacenamiento de equipos tecnológicos y la implementación del sistema biométrico lo que hace indispensable una ampliación que permita optimizar las condiciones de trabajo y seguridad, | J8: Proyectos CAPEX_PIURA - Dropbox | K8: OK | L8: =SUM(M8:O8) -> 9 | M8: 1 | N8: 3 | O8: 5 | Q8: SI | R8: UTP Piura | S8: 70170101 | T8: UTP AV,PANAMERICANA 234 -PIURA | U8: 20000 | V8: 9700 | W8: B | X8: 46082 | Y8: 46111 | Z8: 46082 | AA8: 46111 | AB8: EJECUTADO | AC8: EJECUTADO | AD8: Mantenimiento | AE8: SC-0000116696-2026 | AF8: 46063 | AG8: OC-0000122809-2026 | AH8: 46086 | AI8: MEJ00183 | AJ8: UTP_Piura_Ampliacion_Oficina _TI | AK8: 46055 | AL8: ESEVERINO
A9: 3 | B9: OPS_003 | C9: OPS | D9: Soledad Palacios | H9: Anaqueles para depósito de mantenimiento - Sótano 1 | I9: Materiales y herramientas en desorden impidiendo realizar un adecuado inventario | J9: https://www,dropbox,com/scl/fo/ygr8hf8nc7sv9xb4l0xwd/ALWiM47178yHX-TQzmGJhc0?rlkey=yl7begjvbrhyckomvjk2kiwdg&st=aslk3c2p&dl=0 | K9: OK | L9: =SUM(M9:O9) -> 10 | M9: 4 | N9: 2 | O9: 4 | Q9: SI | R9: UTP Trujillo | S9: 70180103 | T9: UTP NICOLAS PIEROLA - TRUJILLO | U9: 35000 | W9: A | X9: 46174 | Y9: 46295 | AB9: EN PROCESO | AD9: Campus | AE9: SC-0000115856-2026 | AI9: AM001207 | AJ9: UTP_Trujillo_Anaqueles_depósito_mantenimiento_Sótano 1 | AK9: 46055 | AL9: ESEVERINO | AM9: OC en cotización
A10: 4 | B10: OPS_004 | C10: OPS | D10: Marco Bonifaz | H10: Ascensor de escaleras para personas con discapacidad del piso 15 a la terraza en torre A y torre B, | I10: Los ascensores de ambas torres van hasta el piso 15 las personas con discapacidad no pueden acceder a la terraza del piso 16 en torre A tenemos espacios libres y próximamente a Listo y en la terraza de la torre B tenemos también espacios libres y zona de vida universitaria, | J10: EJEMPLO DE ASCENSOR DE ESCALERA PARA DISCAPACITADOS,jpg | K10: OK | L10: =SUM(M10:O10) -> 13 | M10: 3 | N10: 5 | O10: 5 | P10: Revisar di instalación de equipo perjudica evacuación del piso | Q10: SI | R10: UTP Lima Norte | S10: 10220111 | T10: UTP AV,INFANTAS MZ 2E LOTE 28, URB, STA LUISA - LOS OLIVOS | U10: 70000 | W10: A | X10: 46235 | Y10: 46356 | AB10: PENDIENTE | AD10: Infraestructura
A11: 5 | B11: OPS_005 | C11: OPS | D11: Eloy Pocohuanca | F11: epocohuanc@utp,edu,pe | G11: 937 029 622 | H11: Cambio de counter de biblioteca cambio de mesas de sala grupal cambio de Puff de SAE Implementación de sillas para VU | I11: Cambio de counter de biblioteca de mesas grupales de biblioteca de puff de SAE por deterioro implementación de sillas para la sala de vida universitaria y asi se le pueda dar usi incluso para las diversas actividades universitarias (taller etc) | Q11: SI | R11: UTP Chimbote | S11: 70150101 | T11: UTP PASERO DEL MAR MZ C9- LT2 - CHIMBOTE | U11: 15000 | V11: 11085 | W11: B | X11: 46082 | Y11: 46082 | Z11: 46082 | AA11: 46111 | AB11: EJECUTADO | AC11: EJECUTADO | AD11: Proyectos Ops | AE11: SC-0000118185-2026 / SC-0000120820-2026 | AF11: 46098 | AG11: OC-0000121793-2026 / OC-0000124082-2026 | AH11: 46098 | AI11: AM001195 | AJ11: UTP_Chimbote_Cambio_counter biblioteca_Puff de SAE_mesas grupales_implementacion sillas_VU | AK11: 46055 | AL11: ESEVERINO | AM11: generación de SC y OC: 24/02 / 17/03
A12: 6 | B12: OPS_006 | C12: OPS | D12: Carlos Sanchez Pariona | F12: csanchezp@utp,edu,pe | G12: 951 317 089 | H12: Cambio de grifería y trampas en 50 baños de Torre Petit Thoaurs | I12: Para la mejora en la experiencia alumno y su impacto en NPS se requiere cambio de grifería trampas desagüe en 50 baños | J12: https://www,dropbox,com/scl/fi/2htg1gbdek9wr6e2g0y57/Iniciativas-mejora-2025,pptx?rlkey=ucwlfkeatbngte3u1q2nij5lp&st=ukeg7lj8&dl=0 | K12: OK | L12: =SUM(M12:O12) -> 8 | M12: 2 | N12: 5 | O12: 1 | Q12: SI | R12: UTP Lima Centro | S12: 10110204 | T12: UTP PETIT THOU383-385-TORRE II - LIMA | U12: 26000 | V12: 16374.52 | W12: C | X12: 46174 | Y12: 46295 | Z12: 46132 | AB12: EN PROCESO | AD12: Mantenimiento | AE12: SC-0000116432-2026 / SC-0000122792-2026 | AF12: 46119 | AG12: OC-0000125881-2026 / OC-0000128442-2026 | AH12: 07/04 / 30/04 | AI12: MEJ00184 | AJ12: UTP_PTT383-385_Cambio_griferia_trampas _50 baños_Torre II | AK12: 46055 | AL12: ESEVERINO | AM12: SE ENVIÓ NR OC-0000125881-2026
A13: 7 | B13: OPS_007 | C13: OPS | D13: Carlos Sanchez Pariona | F13: csanchezp@utp,edu,pe | G13: 951 317 089 | H13: Cambio de línea de desague en Torre Petit Thoaurs | I13: Cambio de línea matriz de desagüe ambos montantes por constantes atoros, Antigüedad mayor a 20 años | J13: https://www,dropbox,com/scl/fi/2htg1gbdek9wr6e2g0y57/Iniciativas-mejora-2025,pptx?rlkey=ucwlfkeatbngte3u1q2nij5lp&st=ukeg7lj8&dl=0 | K13: OK | L13: =SUM(M13:O13) -> 11 | M13: 1 | N13: 5 | O13: 5 | Q13: SI | R13: UTP Lima Centro | S13: 10110204 | T13: UTP PETIT THOU383-385-TORRE II - LIMA | U13: 87457.3 | V13: 84268.51 | W13: A | X13: 46174 | Y13: 46295 | Z13: 46193 | AB13: EN PROCESO | AD13: Mantenimiento | AE13: SC-0000116816-2026 | AF13: 46063 | AG13: OC-0000133232-2026 | AH13: 46175 | AI13: MEJ00185 | AJ13: UTP_PTT383-385_Cambio_línea desague_Torre II | AK13: 46055 | AL13: ESEVERINO | AO13: Presupuesto se amplia a 87 K
A14: 8 | B14: OPS_008 | C14: OPS | D14: Elmer Raul ILLANES PAUCAR | F14: eillanes@utp,edu,pe | G14: 994 690 404 | H14: Cambio de piso de biblioteca por porcelanato | I14: El piso actual presenta desgaste significativo del material debido al propio uso estando en muy mal estado por algunas zonasadiconal dicho material no ha sido reemplazado desde el 2018, | J14: PISO BIBLIOTECA | K14: OK | L14: =SUM(M14:O14) -> 9 | M14: 3 | N14: 5 | O14: 1 | Q14: SI | R14: UTP Lima Este | S14: 10220108 | T14: UTP N,AYLLON KM11,60 LOTE 96ATE -LIMA | U14: 71200 | V14: 71200 | W14: B | X14: 46082 | Y14: 46082 | Z14: 46082 | AA14: 46111 | AB14: EJECUTADO | AC14: EJECUTADO | AD14: Mantenimiento | AE14: SC-0000116464-2026 | AF14: 46060 | AG14: OC-0000121837-2026 | AH14: 46077 | AI14: MEJ00186 | AJ14: UTP_Ate KM11,60_Cambio_piso biblioteca_porcelanato | AK14: 46055 | AL14: ESEVERINO | AO14: Revisar con Finanzas
A15: 9 | B15: OPS_009 | C15: OPS | D15: Elmer Raul ILLANES PAUCAR | F15: eillanes@utp,edu,pe | G15: 994 690 404 | H15: Cambio de piso de biblioteca por porcelanato | I15: El piso actual presenta desgaste significativo del material debido al propio uso estando en muy mal estado por algunas zonasadiconal dicho material no ha sido reemplazado desde el 2018, | K15: OK | L15: =SUM(M15:O15) -> 9 | M15: 3 | N15: 5 | O15: 1 | Q15: SI | R15: UTP Lima Norte | S15: 10220111 | T15: UTP AV,INFANTAS MZ 2E LOTE 28, URB, STA LUISA - LOS OLIVOS | U15: 130000 | V15: 144753.79 | W15: B | X15: 46082 | Y15: 46082 | Z15: 46082 | AA15: 46111 | AB15: EJECUTADO | AC15: EJECUTADO | AD15: Mantenimiento | AE15: SC-0000116465-2026 | AF15: 46060 | AG15: OC-0000123203-2026 | AH15: 46091 | AI15: MEJ00187 | AJ15: UTP_LN Mz Lote 28_Cambio_piso biblioteca_porcelanato | AK15: 46055 | AL15: ESEVERINO
A16: 10 | B16: OPS_010 | C16: OPS | D16: Gustavo Mallaupoma | H16: Cambio de piso laminado por porcelanato en el laboratorio de terapias física de Sede Central | I16: El piso instalado para el laboratorio de terapia física no es el adecuado al no ser óptimo para alto tránsito así mismo no está dentro del estándar de pisos instalados en otros campus, En la actualidad el piso se encuentra totalmente desgastado y genera una muy mala imagen para los estudiantes, | J16: https://drive,google,com/drive/folders/1P0EWUzgUa6s_t8Xe0GcagbXeceSvYmfn | K16: OK | L16: =SUM(M16:O16) -> 10 | M16: 4 | N16: 5 | O16: 1 | Q16: SI | R16: UTP Lima Centro | S16: 10110201 | T16: UTP PETITTHOURS 116 - LIMA | U16: 30000 | V16: 14355.5 | W16: A | X16: 46082 | Y16: 46082 | Z16: 46082 | AA16: 46111 | AB16: EJECUTADO | AC16: EJECUTADO | AD16: Mantenimiento | AE16: SC-0000117935-2026 | AF16: 46073 | AG16: OC-0000122833-2026 | AH16: 46086 | AI16: MEJ00188 | AJ16: UTP_PTT116_Cambio_piso laminado_porcelanato_laboratorio_terapias fisicas | AK16: 46055 | AL16: ESEVERINO | AM16: Conversar con Fredy
A17: 11 | B17: OPS_011 | C17: OPS | D17: Carlos Sanchez Pariona | F17: csanchezp@utp,edu,pe | G17: 951 317 089 | H17: Cambio de porcelanatos en ambientes críticos con levantamientos/roturas diferente color en Torre Petit Thoaurs, | I17: El porcelanato de 44 ambientes académicos se encuentra levantados y/o rajados, Hay 21 ambientes críticos que se localizan entre el piso 7 y 14,Se adjunta excel en link con el detalle | J17: Porcelanatos TORRE2 | K17: OK | L17: =SUM(M17:O17) -> 9 | M17: 3 | N17: 5 | O17: 1 | Q17: SI | R17: UTP Lima Centro | S17: 10110204 | T17: UTP PETIT THOU383-385-TORRE II - LIMA | U17: 258000 | V17: 156958.9 | W17: B | X17: 46174 | Y17: 46295 | Z17: 46132 | AB17: EN PROCESO | AD17: Mantenimiento | AE17: SC-0000116467-2026 | AF17: 46060 | AG17: OC-0000124295-2026 | AH17: 46100 | AI17: MEJ00189 | AJ17: UTP_PTT383-385_Cambio_porcelanatos_ambientes criticos | AK17: 46055 | AL17: ESEVERINO
A18: 12 | B18: OPS_012 | C18: OPS | D18: Carlos Sanchez Pariona | F18: csanchezp@utp,edu,pe | G18: 951 317 089 | H18: Cambio del techo del comedor | I18: Techo del comedor está en mal estado la limpieza no es suficiente las planchas de policarbonato están descoloridas, Estéticamente impacta en la imagen del Campus se ve mal | J18: TECHO COMEDOR ATE | K18: OK | L18: =SUM(M18:O18) -> 11 | M18: 5 | N18: 5 | O18: 1 | Q18: SI | R18: UTP Lima Este | S18: 10220108 | T18: UTP N,AYLLON KM11,60 LOTE 96ATE -LIMA | U18: 32000 | V18: 46990.9 | W18: A | X18: 46174 | Y18: 46295 | Z18: 46132 | AB18: EN PROCESO | AD18: Mantenimiento | AE18: SC-0000116469-2026 | AF18: 46060 | AG18: OC-0000124831-2026 | AH18: 46105 | AI18: MEJ00190 | AJ18: UTP_Ate KM11,60_Cambio_techo_comedor | AK18: 46055 | AL18: ESEVERINO
A19: 13 | B19: OPS_013 | C19: OPS | D19: VICENTE CAYETANO RODRIGUEZ PASTOR | F19: vrodriguep@utp,edu,pe | G19: 955 141 444 | H19: Cambio sistema de bombeo de presión constante torre A | I19: Sistema de bombeo de agua de torre A tiene mas de 7 años de antigüedad se tiene con frecuencia caidas de presión y deja sin agua a torre A los tableros de control no permite el funcionamiento de 02 bombas a la vez para aliviar la presión, Son dos bombas por Us 12k | J19: 6 | K19: OK | L19: =SUM(M19:O19) -> 9 | M19: 1 | N19: 3 | O19: 5 | Q19: SI | R19: UTP Lima Sur | S19: 10220106 | T19: UTP EL TRIUNFO S/N-VILLA SALVA - LIMA | U19: 128000 | V19: 125982.76 | W19: B | X19: 46082 | Y19: 46082 | Z19: 46082 | AA19: 46111 | AB19: EJECUTADO | AC19: EJECUTADO | AD19: Mantenimiento | AE19: SC-0000116814-2026 | AF19: 46063 | AG19: OC-0000123018-2026 | AH19: 46087 | AI19: MEJ00191 | AJ19: UTP_VES_Cambio_sistema_bombeo presion constante_torre A | AK19: 46055 | AL19: ESEVERINO
A20: 14 | B20: OPS_014 | C20: OPS | D20: Nestor Silva | H20: Construcción de Caseta de Vigilancia | I20: Actualmente no contamos con caseta y el ecritorio en "L" se encuentra expuesto y a riesgo de extravío de llaves y DNI | J20: https://www,dropbox,com/scl/fi/eba9a8xdt27v27lynl3yp/espacio-de-vigilantes-en-sede-sin-caseta,jpg?rlkey=h8ytg6opg0ibyf17t4laksicw&st=thdy8ie3&dl=0 | K20: OK | L20: =SUM(M20:O20) -> 11 | M20: 2 | N20: 4 | O20: 5 | P20: OK a evaluar presupuesto insuficiente | Q20: SI | R20: UTP Ica | S20: 70160101 | T20: UTP SUB EUB-5 SAN JOSE - ICA | U20: 18000 | W20: A | X20: 46235 | Y20: 46356 | AB20: PENDIENTE | AD20: Infraestructura
A21: 15 | B21: OPS_015 | C21: OPS | D21: CARLA CELI | H21: Depósito y estantería para SSUU (en esquina zona deportiva) | Q21: SI | R21: UTP Trujillo | S21: 70180103 | T21: UTP NICOLAS PIEROLA - TRUJILLO | U21: 45000 | W21: B | X21: 46235 | Y21: 46356 | AB21: PENDIENTE | AD21: Infraestructura
A22: 16 | B22: OPS_016 | C22: OPS | D22: Luis García | H22: Equipo de AA para cuarto de servidores torre A | I22: Climatización del cuarto de servidores de la torre A área crítica por contar con equipos de comunicación operativos 24/7 | J22: https://www,dropbox,com/scl/fi/wnlt33yfldc6wo0joscax/Data_CIX,png?rlkey=fmvsqv89rz8up9ygn2qdp9f6x&st=5qsbjec3&dl=0 | K22: OK | L22: =SUM(M22:O22) -> 9 | M22: 4 | N22: 1 | O22: 4 | Q22: SI | R22: UTP Chiclayo | S22: 70120201 | T22: UTP AV, PROGRESO CON AV, EVITAMIENTO S/N - CHICLAYO | U22: 6000 | V22: 6107.66 | W22: B | X22: 46174 | Y22: 46295 | AB22: EN PROCESO | AD22: Mantenimiento | AE22: SC-0000116471-2026 | AF22: 46060 | AG22: SC DEVUELTA | AI22: PROY1379 | AJ22: UTP_Chiclayo_Equipo AA_cuarto_servidores torre A | AK22: 46055 | AL22: ESEVERINO | AM22: Solicitud devuelta responsable no confirma obs de planos
A23: 17 | B23: OPS_017 | C23: OPS | D23: VICENTE CAYETANO RODRIGUEZ PASTOR | F23: vrodriguep@utp,edu,pe | G23: 955 141 444 | H23: Habilitar puntos de agua para sardinel | I23: En convenio con la municipalidad el área de sardinel fue cedida para mantenimiento actualmente al no tener punto de agua no se puede realizar, Se evidencia en el video la actual condición, | J23: Puntos de agua,mp4 | K23: OK | L23: =SUM(M23:O23) -> 8 | M23: 1 | N23: 4 | O23: 3 | Q23: SI | R23: UTP Chimbote | S23: 70150101 | T23: UTP PASERO DEL MAR MZ C9- LT2 - CHIMBOTE | U23: 15000 | V23: 6107.66 | W23: C | X23: 46082 | Y23: 46203 | Z23: 46082 | AA23: 46170 | AB23: EJECUTADO | AC23: EJECUTADO | AD23: Mantenimiento | AE23: SC-0000116786-2026 | AF23: 46063 | AG23: OC-0000122376-2026 | AH23: 46084 | AI23: PROY1380 | AJ23: UTP_Chimbote_Habilitar_puntos agua_sardinel | AK23: 46055 | AL23: ESEVERINO
A24: 18 | B24: OPS_018 | C24: OPS | D24: Katherine Polo | H24: Iluminación del nombre de la Universidad | J24: FOTOS NOMBRE LOGOS UTP | Q24: SI | R24: UTP Lima Sur | S24: 10220106 | T24: UTP EL TRIUNFO S/N-VILLA SALVA - LIMA | U24: - | W24: B | AB24: CANCELADO | AD24: Infraestructura
A25: 19 | B25: OPS_019 | C25: OPS | D25: Katherine Polo | H25: Iluminación del nombre de la Universidad | J25: FOTOS NOMBRE LOGOS UTP | Q25: SI | R25: UTP Lima Norte | S25: 10220111 | T25: UTP AV,INFANTAS MZ 2E LOTE 28, URB, STA LUISA - LOS OLIVOS | U25: 24250 | W25: B | X25: 46235 | Y25: 46356 | AB25: PENDIENTE | AD25: Infraestructura
A26: 20 | B26: OPS_020 | C26: OPS | D26: Katherine Polo | H26: Iluminación del nombre de la Universidad | J26: FOTOS NOMBRE LOGOS UTP | Q26: SI | R26: UTP Lima Centro | S26: 10110102 | T26: UTP AREQUIPA 660- 670 - LIMA | U26: 24250 | W26: B | X26: 46235 | Y26: 46356 | AB26: PENDIENTE | AD26: Infraestructura | AM26: Pendiente en consulta
A27: 21 | B27: OPS_021 | C27: OPS | D27: Katherine Polo | H27: Iluminación del nombre de la Universidad | I27: Las letras negras "Universidad Tecnológica del Perú" sin iluminación pasan desapercibidas en la noche, En SJL ATE si están iluminadas | J27: FOTOS NOMBRE LOGOS UTP | K27: OK | L27: =SUM(M27:O27) -> 9 | M27: 2 | N27: 5 | O27: 2 | P27: OK para evaluar poner iluminación con reflectores | Q27: SI | R27: UTP Lima Centro | S27: 10110204 | T27: UTP PETIT THOU383-385-TORRE II - LIMA | U27: 24250 | W27: B | X27: 46235 | Y27: 46356 | AB27: PENDIENTE | AD27: Infraestructura
A28: 22 | B28: OPS_022 | C28: OPS | D28: Gustavo Mallaupoma | H28: Impermeabilización de los pisos de todos los baños de la torre | I28: Existen filtraciones de agua hacia pisos inferiores en los SSHH del campus cuando se ejecuta la limpieza de los mismos por parte de Limtek, Esto genera daño a las baldosas lo cual implica estar cambiandolas constantemente, | J28: https://www,dropbox,com/scl/fi/ji89dac31y2yls6rsyl4m/Huancayo_Mejoras,pptx?rlkey=sdwbvs1liw2b8mgovq0bq8nn5&st=q1lvojps&dl=0 | K28: OK | L28: =SUM(M28:O28) -> 12 | M28: 3 | N28: 4 | O28: 5 | Q28: SI | R28: UTP Huancayo | S28: 70190101 | T28: UTP AV,CIRCUNVALACIÓN 449 - HUANCAYO | U28: 13000 | V28: 13919.28 | W28: A | X28: 46082 | Y28: 46111 | Z28: 46082 | AA28: 46111 | AB28: EJECUTADO | AC28: EJECUTADO | AD28: Mantenimiento | AE28: SC-0000118739-2026 | AF28: 46081 | AG28: OC-0000123888-2026 | AH28: 46097 | AI28: MEJ00192 | AJ28: UTP_Hcyo_Impermeabilizacion _pisos_baños_torre | AK28: 46055 | AL28: ESEVERINO
A29: 23 | B29: OPS_023 | C29: OPS | D29: Ricardo Jacobo | H29: Impermeabilización y revestimiento de azotea | I29: Para evitar las filtraciones es necesario contar con una impermeabilización de toda la azotea completa, No tiene impermeabilización y presenta filtraciones constantes , En el Bloque C han parchado por zonas puntuales cuando han habido filtraciones | J29: 3 | K29: OK | L29: =SUM(M29:O29) -> 9 | M29: 1 | N29: 5 | O29: 3 | P29: OK para evaluar | Q29: SI | R29: UTP Lima Sur | S29: 10220106 | T29: UTP EL TRIUNFO S/N-VILLA SALVA - LIMA | U29: 140000 | W29: B | X29: 46235 | Y29: 46356 | AB29: PENDIENTE | AD29: Infraestructura | AM29: Se modificó monto de 160K a 140K | AO29: Revisar cambiar de monto
A30: 24 | B30: OPS_024 | C30: OPS | D30: Eloy Pocohuanca/Carlos S, | F30: epocohuanc@utp,edu,pe | G30: 937 029 622 | H30: Implemenrar área libre para alumnos en el sum del piso 15 Torre 2, Local no tiene áreas libres para alumnos | I30: Propuesta de retirar la tabiquería y puerta del SUM del piso 15 para poder ganar espacio para aumentar dos mesas más adicionales al ambiente, Tamaño final 45,6 m2, El uso del ambiente es intensivo y es uno de los pocos ambientes con los que los alumnos cuentan para avanzar sus trabajos con laptop y en horario de refrigerio para poder almorzar, Adicionalmente incluye la renovación de 8 mesas y 32 sillas más compra de 2 mesas y 8 sillas, | J30: https://www,dropbox,com/scl/fo/045w1pv87upfjolydrkn3/APvbKb6m3Z9c9rvOZuyvhSI?rlkey=flxw6v94kr6egfxz6leroshzj&st=fps3xzwp&dl=0 | K30: OK | L30: =SUM(M30:O30) -> 11 | M30: 5 | N30: 5 | O30: 1 | Q30: SI | R30: UTP Lima Centro | S30: 10110204 | T30: UTP PETIT THOU383-385-TORRE II - LIMA | U30: 20000 | W30: A | X30: 46266 | Y30: 46326 | AB30: PENDIENTE | AD30: Proyectos Ops | AE30: SC-0000143394-2026 | AF30: 46274 | AI30: PROY1381 | AJ30: UTP_PTT_383-385_Implementar_area libre_alumnos_piso 15 Torre 2 | AK30: 46055 | AL30: ESEVERINO | AM30: Conversar con Jossi coordina Julio
A31: 25 | B31: OPS_025 | C31: OPS | D31: Marco Bonifaz | H31: Implementación de almacén en azotea | P31: OK a evaluar se debe tener en cuanta trámite de conformidad d eobra en curso | Q31: SI | R31: UTP Piura | S31: 70170101 | T31: UTP AV,PANAMERICANA 234 -PIURA | U31: 80000 | W31: B | X31: 46235 | Y31: 46356 | AB31: PENDIENTE | AD31: Infraestructura
A32: 26 | B32: OPS_026 | C32: OPS | D32: Marco Bonifaz | H32: Implementación de depósito adicional | I32: No contamos con espacio suficiente para el almacenamiento de diversos materiales activos y demás objetos los cuales son de uso continuo en sede lo que nos obliga a guardarlos en espacios no adecuados, Lo cual a la vista de la comunidad universitaria e instituciones reguladoras serian altamente e inclusi motivo de sanción, Se propone la utilización de dos espacios para vehículos del estacionamiento del semisótano para esta nueva implementación ya que actualmente contamos espacios en el patio los cuales pueden servir para suplir la necesidad generada de espacios para el estacionamiento, | Q32: SI | R32: UTP Huancayo | S32: 70190101 | T32: UTP AV,CIRCUNVALACIÓN 449 - HUANCAYO | U32: 15000 | W32: B | X32: 46235 | Y32: 46356 | AB32: PENDIENTE | AD32: Infraestructura
A33: 27 | B33: OPS_027 | C33: OPS | D33: Gustavo Mallaupoma | H33: Implementación de puntos eléctricos en el patio | I33: En sede no contamos con espacios amplios para el desarrollo de eventos muchos de ellos se han realizado en el patio como el taller de danzas aniversario de la sede feria de emprendimiento entre otras, Estas actividades demandan contar con puntos eléctricos para que los equipos funcionen y se realice las actividades convenientemente, | J33: Fotos para mejoras 1,pptx | K33: OK | L33: =SUM(M33:O33) -> 10 | M33: 4 | N33: 2 | O33: 4 | Q33: SI | R33: UTP Huancayo | S33: 70190101 | T33: UTP AV,CIRCUNVALACIÓN 449 - HUANCAYO | U33: 18000 | V33: 12991.8 | W33: A | X33: 46082 | Y33: 46082 | Z33: 46082 | AA33: 46111 | AB33: EJECUTADO | AC33: EJECUTADO | AD33: Mantenimiento | AE33: SC-0000118740-2026 | AF33: 46081 | AG33: OC-0000123883-2026 | AH33: 46097 | AI33: MEJ00193 | AJ33: UTP_Hcyo_Implementacion_puntos electricos_patio | AK33: 46055 | AL33: ESEVERINO
A34: 28 | B34: OPS_028 | C34: OPS | D34: Gustavo Mallaupoma | H34: Implementación de sumideros en el laboratorio de procesos industriales | I34: Implementar cuatro sumideros adicionales en el piso del laboratorio, Cuando se realiza la limpieza de equipos el agua se queda acumulada debajo de estas y la limpieza del ambiente demora, La limpiea toma mas tiempo del previsto para el asistente del laboratorio, Asi mismo; el riesgo accidentes por el piso que se vuelve resbaloso | J34: Fotos para mejoras 1,pptx | K34: OK | L34: =SUM(M34:O34) -> 10 | M34: 4 | N34: 2 | O34: 4 | Q34: SI | R34: UTP Huancayo | S34: 70190101 | T34: UTP AV,CIRCUNVALACIÓN 449 - HUANCAYO | U34: 10000 | V34: 8510.48 | W34: A | X34: 46082 | Y34: 46172 | Z34: 46082 | AA34: 46172 | AB34: EJECUTADO | AC34: EJECUTADO | AD34: Mantenimiento | AE34: SC-0000118741-2026 | AF34: 46081 | AG34: OC-0000123225-2026 | AH34: 46091 | AI34: MEJ00194 | AJ34: UTP_Hcyo_Implementacion_sumideros_laboratorio | AK34: 46055 | AL34: ESEVERINO
A35: 29 | B35: OPS_029 | C35: OPS | D35: Eloy / Raul | H35: Implementación de tomacorrientes para mesas de salas de estudio en biblioteca | I35: Suminstro e instalación de 48 puntos de energia | J35: Tacna y Arica – Mesas biblioteca,pdf | K35: OK | L35: =SUM(M35:O35) -> 11 | M35: 4 | N35: 3 | O35: 4 | Q35: SI | R35: UTP Arequipa | S35: 70110101 | T35: UTP TACNA-ARICA 158-160-162 - AREQUIPA | U35: 20000 | W35: A | X35: 46203 | Y35: 46325 | AB35: PENDIENTE | AD35: Proyectos Ops / Mantenimiento | AE35: SC-0000118273-2026 | AF35: 46077 | AG35: SC DEVUELTA | AI35: MEJ00195 | AJ35: UTP_Arq 158-160_Implementacion_tomacorrientes_mesas_biblioteca | AK35: 46055 | AL35: ESEVERINO | AM35: SC devuelta a la espera de nuevo alcance | AP35: ELOY
A36: 31 | B36: OPS_030 | C36: OPS | D36: Eloy / Raul | H36: Implementación de tomacorrientes para mesas de salas de estudio en biblioteca | I36: Renovación de mobiliario con integración de puntos eléctricos retráctiles en mesas de trabajo (sala lectura 01) y el sala lectura 2 se mantiene el mobiliario | J36: https://utpedupe,sharepoint,com/:f:/s/OperacionesCIX/EuVMG6DEAQZNp7fh5H-BPcIBEBuJg4Cyzmy5w2K40DH5-g?e=sAAUob | K36: OK | L36: =SUM(M36:O36) -> 11 | M36: 4 | N36: 3 | O36: 4 | Q36: SI | R36: UTP Chiclayo | S36: 70120201 | T36: UTP AV, PROGRESO CON AV, EVITAMIENTO S/N - CHICLAYO | U36: 21000 | V36: 21000 | W36: A | X36: 46174 | Y36: 46264 | AB36: EJECUTADO | AC36: PENDIENTE | AD36: Proyectos Ops / Mantenimiento | AE36: SC-0000137984-2026 | AF36: 46225 | AG36: OC-0000142670-2026 | AH36: 46100 | AI36: MEJ00196 | AJ36: UTP_Chiclayo_Implementacion_tomacorrientes_mesas_biblioteca | AK36: 46055 | AL36: ESEVERINO | AM36: Se canceló OC-0000124398-2026 por nuevo alcance/ OC-0000142670-2026 nr
A37: 32 | B37: OPS_031 | C37: OPS | D37: Eloy / Raul | H37: Implementación de tomacorrientes para mesas de salas de estudio en biblioteca | I37: Se adjunta cotización para energizar 10 mesas con toma eléctrica doble (20 puntos de energía) | J37: https://utpedupe-my,sharepoint,com/:i:/g/personal/etirado_utp_edu_pe/Eb8rAbMwJuBHi885UHeD0T0BSpgRhLu8HVJCDLvxjOF6IA?e=QkVs4N | K37: OK | L37: =SUM(M37:O37) -> 11 | M37: 4 | N37: 3 | O37: 4 | Q37: SI | R37: UTP Chimbote | S37: 70150101 | T37: UTP PASERO DEL MAR MZ C9- LT2 - CHIMBOTE | U37: 15800 | V37: 15444.22 | W37: A | X37: 46082 | Y37: 46203 | Z37: 46082 | AA37: 46143 | AB37: EJECUTADO | AC37: PENDIENTE | AD37: Proyectos Ops / Mantenimiento | AE37: SC-0000118552-2026 | AF37: 46079 | AG37: OC-0000124582-2026 | AH37: 46102 | AI37: MEJ00197 | AJ37: UTP_Chimbote_Implementacion_tomacorrientes_mesas_biblioteca | AK37: 46055 | AL37: ESEVERINO | AM37: Pendiente de NR
A38: 33 | B38: OPS_032 | C38: OPS | D38: Eloy / Raul | H38: Implementación de tomacorrientes para mesas de salas de estudio en biblioteca | I38: Se cuenta con una parte de las mesas con puntos de energía dento de biblioteca y se mapearon un total de 52 puntos de energía faltantes por lo cual se requiere la energización en 20 puntos para mesas en la sala de lectura y 32 puntos para mesas en la sala de estudio, El costo es referencial en base a la instalación previa de 9 puntos de energía en uno de los laboratorios del campus, | J38: INSTALACIÓN DE PUNTOS DE ENERGIA EN BIBLIOTECA | K38: OK | L38: =SUM(M38:O38) -> 11 | M38: 4 | N38: 3 | O38: 4 | Q38: SI | R38: UTP Huancayo | S38: 70190101 | T38: UTP AV,CIRCUNVALACIÓN 449 - HUANCAYO | U38: 18000 | V38: 16475.75 | W38: A | X38: 46082 | Y38: 46111 | Z38: 46082 | AA38: 46111 | AB38: EJECUTADO | AC38: EJECUTADO | AD38: Proyectos Ops / Mantenimiento | AE38: SC-0000117917-2026 | AF38: 46073 | AG38: OC-0000124862-2026 | AH38: 46105 | AI38: MEJ00198 | AJ38: UTP_Hcyo_Implementacion_tomacorrientes_mesas_biblioteca | AK38: 46055 | AL38: ESEVERINO
A39: 34 | B39: OPS_033 | C39: OPS | D39: Eloy / Raul | H39: Implementación de tomacorrientes para mesas de salas de estudio en biblioteca | I39: Se requiere instalar 42 puntos electricos para biblioteca, | J39: https://utpedupe-my,sharepoint,com/personal/hleon_utp_edu_pe/_layouts/15/onedrive,aspx?id=%2Fpersonal%2Fhleon%5Futp%5Fedu%5Fpe%2FDocuments%2FUTP%2FAREA%20OPERACIONES%20%2D%20COMPARTIDO%2FCAPEX%20ADICIONALES%202026%2FEnergizar%20mesas%20de%20Biblioteca&viewid=dc302f51%2D364c%2D45d8%2Db630%2D7c45cef7440a&ga=1 | K39: OK | L39: =SUM(M39:O39) -> 11 | M39: 4 | N39: 3 | O39: 4 | Q39: SI | R39: UTP Ica | S39: 70160101 | T39: UTP SUB EUB-5 SAN JOSE - ICA | U39: 24260 | V39: 14030.27 | W39: A | X39: 46082 | Y39: 46172 | Z39: 46082 | AA39: 46142 | AB39: EJECUTADO | AC39: EJECUTADO | AD39: Proyectos Ops / Mantenimiento | AE39: SC-0000117916-2026 | AF39: 46073 | AG39: OC-0000124429-2026 | AH39: 46100 | AI39: MEJ00199 | AJ39: UTP_Ica_Implementacion_tomacorrientes_mesas_biblioteca | AK39: 46055 | AL39: ESEVERINO | AM39: Logistica cambió codigo de proyecto a Generico, a solicitud de contabilidad
A40: 35 | B40: OPS_034 | C40: OPS | D40: Eloy / Raul | H40: Implementación de tomacorrientes para mesas de salas de estudio en biblioteca | I40: Se requiere habilitación de puntos eléctricos para 9 mesas, Se puede manejar internamente con área de mantenimiento, | J40: https://utpedupe-my,sharepoint,com/:f:/g/personal/grubio_utp_edu_pe/Emjzi9UGTElEiur-35Qm26UBtzTIdw9dPmfcLFeHzKzheg?e=MUMhXJ | K40: OK | L40: =SUM(M40:O40) -> 11 | M40: 4 | N40: 3 | O40: 4 | Q40: SI | R40: UTP Piura | S40: 70170101 | T40: UTP AV,PANAMERICANA 234 -PIURA | U40: 2500 | V40: 2183 | W40: A | X40: 46082 | Y40: 46172 | Z40: 46082 | AA40: 46127 | AB40: EJECUTADO | AC40: EJECUTADO | AD40: Proyectos Ops / Mantenimiento | AE40: SC-0000118063-2026 | AF40: 46073 | AG40: OC-0000123121-2026 | AH40: 46090 | AI40: MEJ00200 | AJ40: UTP_Piura_Implementacion_tomacorrientes_mesas_biblioteca | AK40: 46055 | AL40: ESEVERINO
A41: 36 | B41: OPS_035 | C41: OPS | D41: Eloy / Raul | H41: Implementación de tomacorrientes para mesas de salas de estudio en biblioteca | I41: Habilitación de puntos eléctricos para mesas de biblioteca 33 puntos | J41: Mesa de Estudios electrificada | K41: OK | L41: =SUM(M41:O41) -> 11 | M41: 4 | N41: 3 | O41: 4 | Q41: SI | R41: UTP Trujillo | S41: 70180103 | T41: UTP NICOLAS PIEROLA - TRUJILLO | U41: 17109 | V41: 17930.18 | W41: A | X41: 46143 | Y41: 46203 | Z41: 46143 | AA41: 46143 | AB41: EJECUTADO | AC41: EJECUTADO | AD41: Proyectos Ops / Mantenimiento | AE41: SC-0000117919-2026 | AF41: 46073 | AG41: OC-0000127316-2026 | AH41: 46134 | AI41: MEJ00201 | AJ41: UTP_Trujillo_Implementacion_tomacorrientes_mesas_biblioteca | AK41: 46055 | AL41: ESEVERINO
A42: 37 | B42: OPS_036 | C42: OPS | D42: Eloy / Raul | H42: Implementación de tomacorrientes para mesas de salas de estudio en biblioteca (ATE LS LN TTAPACIFICO) | J42: Tomacorrientes Salas Estudio | Q42: SI | R42: UTP Lima Este | S42: 10220108 | T42: UTP N,AYLLON KM11,60 LOTE 96ATE -LIMA | U42: 0 | V42: 0 | W42: A | X42: 46082 | Y42: 46082 | Z42: 46082 | AA42: 46111 | AB42: EJECUTADO | AC42: EJECUTADO | AD42: Proyectos Ops / Mantenimiento | AE42: SC-0000116464-2026 | AF42: 46060 | AG42: OC-0000121837-2026 | AH42: 46077 | AI42: MEJ00202 | AJ42: UTP_Ate KM 11,60_Implementacion_tomacorrientes_mesas_biblioteca | AK42: 46055 | AL42: ESEVERINO | AM42: Encargado solicita anulacion de SC-0000117924-2026 (SE ATENDIÓ CON LA OC-0000121837-2026) | AO42: Revisar con Finanzas
A43: 38 | B43: OPS_037 | C43: OPS | D43: Eloy / Raul | H43: Implementación de tomacorrientes para mesas de salas de estudio en biblioteca (ATE LS LN TTAPACIFICO) | J43: Tomacorrientes Salas Estudio | Q43: SI | R43: UTP Lima Sur | S43: 10220106 | T43: UTP EL TRIUNFO S/N-VILLA SALVA - LIMA | U43: 17200 | V43: 17154.91 | W43: A | X43: 46082 | Y43: 46125 | Z43: 46082 | AA43: 46125 | AB43: EJECUTADO | AC43: EJECUTADO | AD43: Proyectos Ops / Mantenimiento | AE43: SC-0000117929-2026 | AF43: 46073 | AG43: OC-0000124180-2026 | AH43: 46099 | AI43: MEJ00203 | AJ43: UTP_VES_Implementacion_tomacorrientes_mesas_biblioteca | AK43: 46055 | AL43: ESEVERINO
A44: 39 | B44: OPS_038 | C44: OPS | D44: Eloy / Raul | H44: Implementación de tomacorrientes para mesas de salas de estudio en biblioteca (ATE LS LN TTAPACIFICO) | J44: Tomacorrientes Salas Estudio | Q44: SI | R44: UTP Lima Norte | S44: 10220111 | T44: UTP AV,INFANTAS MZ 2E LOTE 28, URB, STA LUISA - LOS OLIVOS | U44: 17200 | W44: A | X44: 46174 | Y44: 46356 | AB44: PENDIENTE | AD44: Proyectos Ops / Mantenimiento | AI44: MEJ00204 | AJ44: UTP_LN MZ 2E Lote 28_Implementacion_tomacorrientes_mesas_biblioteca | AK44: 46055 | AL44: ESEVERINO | AM44: Reunir con los involucrados
A45: 40 | B45: OPS_039 | C45: OPS | D45: Eloy / Raul | H45: Implementación de tomacorrientes para mesas de salas de estudio en biblioteca (ATE LS LN TTAPACIFICO) | J45: Tomacorrientes Salas Estudio | Q45: SI | R45: UTP Lima Centro | S45: 10110205 | T45: UTP AV, AREQUIPA 265-279 - LIMA | U45: 17200 | V45: 22192.19 | W45: A | X45: 46143 | Y45: 46203 | Z45: 46143 | AA45: 46143 | AB45: EJECUTADO | AC45: EJECUTADO | AD45: Proyectos Ops / Mantenimiento | AE45: SC-0000120469-2026 | AF45: 46094 | AG45: OC-0000126973-2026 | AH45: 46131 | AI45: MEJ00205 | AJ45: UTP_Arq265-279_Implementacion_tomacorrientes_mesas_biblioteca | AK45: 46055 | AL45: ESEVERINO
A46: 41 | B46: OPS_040 | C46: OPS | D46: Eloy / Raul | H46: Implementación de tomacorrientes para mesas de salas de estudio en biblioteca (ATE LS LN TTAPACIFICO) | I46: Actualmente los alumnos necesitan enchufes para sus laptops en las salas de estudio, Desenchufan las computadores de bilbioteca y colocan extensiones para el uso de sus laptops, Esto es un riesgo e impide la evacuación en caso de sismos o algún peligro, San Juan ya tiene | J46: Tomacorrientes Salas Estudio | K46: OK | L46: =SUM(M46:O46) -> 12 | M46: 5 | N46: 5 | O46: 2 | Q46: SI | R46: UTP Lima Centro | S46: 10110102 | T46: UTP AREQUIPA 660- 670 - LIMA | U46: 17200 | V46: 12434.95 | W46: A | X46: 46082 | Y46: 46111 | Z46: 46082 | AA46: 46111 | AB46: EJECUTADO | AC46: EJECUTADO | AD46: Proyectos Ops / Mantenimiento | AE46: SC-0000119824-2026 | AF46: 46091 | AG46: OC-0000124005-2026 | AH46: 46098 | AI46: MEJ00206 | AJ46: UTP_Arq660-670_Implementacion_tomacorrientes_mesas_biblioteca | AK46: 46055 | AL46: ESEVERINO
A47: 42 | B47: OPS_041 | C47: OPS | D47: Marcia Lizárraga | H47: Implementación de tres muebles para guardar mochilas | I47: Se requiere la adquisición de tres mochileros para los laboratorios de fluidos y turbomáquinas elasticidad y resistencia de materiales y arquitectura de computadoras debido a que los estudiantes no tienen donde colocar sus mochilas motivo por el cual lo dejan en el piso obstaculizando asi las salidas | J47: Fotos para mejoras 1,pptx | K47: OK | L47: =SUM(M47:O47) -> 10 | M47: 4 | N47: 2 | O47: 4 | Q47: SI | R47: UTP Huancayo | S47: 70190101 | T47: UTP AV,CIRCUNVALACIÓN 449 - HUANCAYO | U47: 4000 | V47: 2880 | W47: A | X47: 46113 | Y47: 46203 | Z47: 46113 | AA47: 46157 | AB47: EJECUTADO | AC47: EJECUTADO | AD47: Campus | AE47: SC-0000115857-2026 | AF47: 46055 | AG47: OC-0000123917-2026 | AH47: 46097 | AI47: AM001196 | AJ47: UTP_Hcyo_Implementacion_muebles_guardar mochilas | AK47: 46055 | AL47: ESEVERINO
A48: 43 | B48: OPS_042 | C48: OPS | D48: Freddy Valderrama | H48: Implementar aire acondicionado SAE TyA | I48: Implementar sistema de aire acondicionado | J48: 25,TyA - Aire acondicionado SAE,mp4 | K48: OK | L48: =SUM(M48:O48) -> 12 | M48: 5 | N48: 4 | O48: 3 | P48: OK a evaluar contra carga eléctrica disponible | Q48: SI | R48: UTP Arequipa | S48: 70110101 | T48: UTP TACNA-ARICA 158-160-162 - AREQUIPA | U48: 250000 | W48: A | X48: 46235 | Y48: 46356 | AB48: EN PROCESO | AD48: Infraestructura
A49: 44 | B49: OPS_043 | C49: OPS | D49: Freddy Valderrama | H49: Implementar aire acondicionado, CAD - Parra 1 | I49: OK a evaluar contra carga eléctrica disponible | P49: OK a evaluar contra carga eléctrica disponible | Q49: SI | R49: UTP Arequipa | S49: 70110103 | T49: UTP PARRA 201-203 - AREQUIPA | U49: 200000 | W49: A | X49: 46235 | Y49: 46356 | AB49: EN PROCESO | AD49: Infraestructura
A50: 45 | B50: OPS_044 | C50: OPS | D50: Freddy Valderrama | H50: Implementar aire acondicionado, CAD - Taca y Arica | I50: OK a evaluar contra carga eléctrica disponible | P50: OK a evaluar contra carga eléctrica disponible | Q50: SI | R50: UTP Arequipa | S50: 70110101 | T50: UTP TACNA-ARICA 158-160-162 - AREQUIPA | U50: 250000 | W50: A | X50: 46235 | Y50: 46356 | AB50: EN PROCESO | AD50: Infraestructura
A51: 46 | B51: OPS_045 | C51: OPS | D51: Eloy Pocohuanca | F51: epocohuanc@utp,edu,pe | G51: 937 029 622 | H51: Implementar área libre para alumnos en el piso 3 de Torre Petit Thouars,Local no tiene áreas libres para alumnos | I51: Reemplazar el deposito (ex isla de post producción) del piso 3 por la implemnetación de area común, | J51: https://www,dropbox,com/scl/fo/iyqy9pj6dts10n3czpo2v/ANjKal-i5QRmzaXzwUAebb8?rlkey=9u7gfkw3ftyy7jiffcui4asfv&st=s6mkblnw&dl=0 | K51: OK | L51: =SUM(M51:O51) -> 11 | M51: 5 | N51: 5 | O51: 1 | Q51: SI | R51: UTP Lima Centro | S51: 10110204 | T51: UTP PETIT THOU383-385-TORRE II - LIMA | U51: 20000 | V51: 1919.9072 | W51: A | X51: 46174 | Y51: 46366 | AB51: EN PROCESO | AD51: Proyectos Ops | AE51: SC-0000137449-2026 | AG51: OC-0000142547-2026 | AI51: PROY1382 | AJ51: UTP_PTT383-385_Implementar_area libre_alumnos_piso 3 Torre II | AK51: 46055 | AL51: ESEVERINO | AM51: Conversar con Jossi/ OC-0000142547-2026 TIENE NR/
A52: 47 | B52: OPS_046 | C52: OPS | D52: CESAR JUNIOR LLERENA AMESQUITA / Elmer Raul ILLANES PAUCAR | F52: cllerena@utp,edu,pe / eillanes@utp,edu,pe | G52: 979 717 991 / 994 690 404 | H52: Implementar bebedero adicional (1) Parra 2 | I52: Habilitar punto de agua para bebedero en Piso 1 | J52: 07,Parra 2 - Bebedero,mp4 | K52: OK | L52: =SUM(M52:O52) -> 9 | M52: 3 | N52: 3 | O52: 3 | Q52: SI | R52: UTP Arequipa | S52: 70110107 | T52: UTP PARRA WASHINGT 217-219 AREQUIPA | U52: 20000 | V52: 4625.01 | W52: B | X52: 46143 | Y52: 46203 | AB52: EJECUTADO | AC52: EJECUTADO | AD52: Campus / Mantenimiento | AE52: SC-0000116523-2026 | AF52: 46063 | AG52: OC-0000125153-2026 | AH52: 46107 | AI52: AM001197 | AJ52: UTP_Tacna Parra_Implementar_bebedero | AK52: 46055 | AL52: ESEVERINO | AM52: SC-0000119664-2026 cancelada
A53: 48 | B53: OPS_047 | C53: OPS | D53: Paola Revilla | H53: IMPLEMENTAR BEBEDEROS ADICIONALES (2) | I53: IMPLEMENTAR 3 BEBEDEROS CON DISPENSADOR ADICIONALES EN CADA TORRE, Actual hay 4 2 en cada torre TORRE A PISOS 4 6 Y AZOTEA, TORRE B PISOS 4 6 Y PATIO POSTERIOR PERMITE MEJORAR EL BIENESTAR DE LOS ESTUDIANTES, | J53: https://www,dropbox,com/scl/fo/cw5j6yx36j8ewdfsf8jm3/AMBbmgBy5gExys4L1xTXwyA?rlkey=mcloivayf24t39et30me9z5os&dl=0 | K53: OK | L53: =SUM(M53:O53) -> 10 | M53: 4 | N53: 5 | O53: 1 | Q53: SI | R53: UTP SJL | S53: 10220110 | T53: UTP AV,SOL SUB LT 13B MZG SJL - LIMA | U53: 14000 | V53: 4531.2 | W53: A | X53: 46244 | Y53: 46295 | Z53: 46082 | AB53: EN PROCESO | AD53: Campus | AE53: SC-0000115982-2026 | AF53: 46056 | AG53: OC-0000126066-2026 | AH53: 46121 | AI53: AM001198 | AJ53: UTP_SJL_Implementar_bebederos | AK53: 46055 | AL53: ESEVERINO | AM53: Consultar con Campus solicitar # de solicitud
A54: 49 | B54: OPS_048 | C54: OPS | D54: Giovanni Ricaza | H54: Implementar bebederos en pisos 3 7 y 10 en sede Pacifico | I54: Impacto positivo en servicio al alumno ya que la sede no cuenta con bebederos estándares como las otras sedes | J54: Bebederos en piso 1 3 y 9 | K54: OK | L54: =SUM(M54:O54) -> 10 | M54: 4 | N54: 5 | O54: 1 | Q54: SI | R54: UTP Lima Centro | S54: 10110102 | T54: UTP AREQUIPA 660- 670 - LIMA | U54: 18000 | V54: 14632 | W54: A | X54: 46082 | Y54: 46172 | Z54: 46082 | AA54: 46157 | AB54: EJECUTADO | AC54: EJECUTADO | AD54: Campus | AE54: SC-0000115953-2026 | AF54: 46056 | AG54: OC-0000122652-2026 | AH54: 46085 | AI54: AM001199 | AJ54: UTP_Arq660-670_Implementar_bebederos_pisos 37 y 10 | AK54: 46055 | AL54: ESEVERINO
A55: 50 | B55: OPS_049 | C55: OPS | D55: Carlos Sanchez Pariona | F55: csanchezp@utp,edu,pe | G55: 951 317 089 | H55: Implementar tomas eléctricas en la azotea Torre A | I55: IMPLEMENTAR TOMAS ELÉCTRICAS DE ENERGIA EN LAS BAJANTES DE LOS TECHOS YA IMPLEMENTADOS ADICIONAL IMPLEMENTAR PUNTOS ELÉCTRICOS Y REPISAS FLOTANTES EN LAS COLUMNAS CILINDRICAS ESTRUCTURALES AMBAS INSTALACIONES PERMITEN PROVEER A LOS ALUMNOS,CON PUNTOS DE RECARGA DE APARATOS ELECTRÓNICOS | J55: https://www,dropbox,com/scl/fo/l0mm27m8nkjtmmc701rmj/APmOzac_jSv1DPLKjmuWBAQ?rlkey=spq9ps3s4j39iyu6zvxh5jkgr&dl=0 | K55: OK | L55: =SUM(M55:O55) -> 11 | M55: 5 | N55: 5 | O55: 1 | Q55: SI | R55: UTP SJL | S55: 10220110 | T55: UTP AV,SOL SUB LT 13B MZG SJL - LIMA | U55: 52000 | V55: 8138.46 | W55: A | X55: 46174 | Y55: 46295 | Z55: 46134 | AB55: EN PROCESO | AD55: Mantenimiento | AE55: SC-0000116817-2026 | AF55: 46063 | AG55: OC-0000123956-2026 | AH55: 46097 | AI55: MEJ00207 | AJ55: UTP_SJL_Implementar_tomas electricas_azotea Torre A | AK55: 46055 | AL55: ESEVERINO | AM55: NR OC-0000123956-2026 enviada, falta nuevos alcances para culminar
A56: 51 | B56: OPS_050 | C56: OPS | D56: Carlos Sanchez Pariona | F56: csanchezp@utp,edu,pe | G56: 951 317 089 | H56: Instalación de extractores en baños damas varones y discapacitados en Torre Petit Thoaurs | I56: Solo hay extractores en baños varones del piso 1 al 5, Se necesita instalar del 1 al 15 en baño damas y discapacitados y baño de varones del piso 6 al 15, Debido a malos olores en los 40 baños | J56: https://www,dropbox,com/scl/fi/2htg1gbdek9wr6e2g0y57/Iniciativas-mejora-2025,pptx?rlkey=ucwlfkeatbngte3u1q2nij5lp&st=ukeg7lj8&dl=0 | K56: OK | L56: =SUM(M56:O56) -> 10 | M56: 4 | N56: 5 | O56: 1 | Q56: SI | R56: UTP Lima Centro | S56: 10110204 | T56: UTP PETIT THOU383-385-TORRE II - LIMA | U56: 60000 | W56: A | X56: 46174 | Y56: 46295 | AB56: EN PROCESO | AD56: Mantenimiento | AE56: SC-0000116822-2026 | AF56: 46063 | AG56: SC DEVUELTA | AI56: AM001200 | AJ56: UTP_PTT383-385_Instalacion_extractores_SSHH | AK56: 46055 | AL56: ESEVERINO | AM56: SC DEVUELTA POR REDIFINIR NUEVO ALCANCE TECNICO
A57: 52 | B57: OPS_051 | C57: OPS | D57: Luis García | H57: la implementación de equipos de HVAC en los cuartos de data center del piso 6 y piso 8 | I57: SOLICITADO POR ELIDA | K57: OK | L57: =SUM(M57:O57) -> 9 | M57: 1 | N57: 3 | O57: 5 | Q57: SI | R57: UTP Lima Norte | S57: 10220111 | T57: UTP AV,INFANTAS MZ 2E LOTE 28, URB, STA LUISA - LOS OLIVOS | U57: 20000 | V57: 7977.52 | W57: B | X57: 46233 | Y57: 46295 | Z57: 46193 | AB57: EN PROCESO | AD57: Mantenimiento | AE57: SC-0000116474-2026 | AF57: 46060 | AG57: OC-0000133497-2026 | AH57: 46177 | AI57: PROY1383 | AJ57: UTP_LN MZ 2E Lote 28_Implementacion_equipos HVAC_cuartos data enter_piso 6 y piso 8 | AK57: 46055 | AL57: ESEVERINO | AM57: OC-0000133497-2026 TIENE NR/
A58: 53 | B58: OPS_052 | C58: OPS | D58: Elmer Raul ILLANES PAUCAR | F58: eillanes@utp,edu,pe | G58: 994 690 404 | H58: Mejorar Iluminación en el perímetro de Sede Central (28 de julio y Petit Thouars) y en LN (frontis posterior) | J58: ILUMINACION PERIMETRO 2026 | Q58: SI | R58: UTP Lima Centro | S58: 10110201 | T58: UTP PETITTHOURS 116 - LIMA | U58: 21500 | V58: 36989.6 | W58: B | X58: 46082 | Y58: 46082 | Z58: 46082 | AA58: 46111 | AB58: EJECUTADO | AC58: EJECUTADO | AD58: Mantenimiento | AE58: SC-0000116624-2026 | AF58: 46062 | AG58: OC-0000122223-2026 | AH58: 46080 | AI58: MEJ00208 | AJ58: UTP_PTT116_Mejorar Iluminacion en el perimetro de Sede Central (28 de julio y Petit Thouars) y en LN (frontis posterior) | AK58: 46055 | AL58: ESEVERINO
A59: 54 | B59: OPS_053 | C59: OPS | D59: Elmer Raul ILLANES PAUCAR | F59: eillanes@utp,edu,pe | G59: 994 690 404 | H59: Mejorar Iluminación en el perímetro de Sede Central (28 de julio y Petit Thouars) y en LN (frontis posterior) | I59: Se requiere iluminación perimetral en Sede Central por el lado de 28 de Julio y Petit Thouars, Y alumbrar el lado derecho del frontis de LN en el cerco perimetral y parte posterior de la sede | J59: ILUMINACION PERIMETRO 2026 | K59: OK | L59: =SUM(M59:O59) -> 9 | M59: 4 | N59: 4 | O59: 1 | Q59: SI | R59: UTP Lima Norte | S59: 10220111 | T59: UTP AV,INFANTAS MZ 2E LOTE 28, URB, STA LUISA - LOS OLIVOS | U59: 21500 | V59: 21634.75 | W59: B | X59: 46233 | Y59: 46295 | AB59: EN PROCESO | AD59: Mantenimiento | AE59: SC-0000116634-2026 | AF59: 46062 | AG59: OC-0000138271-2026 | AH59: 46205 | AI59: MEJ00209 | AJ59: UTP_LN_MZ 2E Lote 28_Mejorar Iluminacion en el perimetro de Sede Central (28 de julio y Petit Thouars) y en LN (frontis posterior) | AK59: 46055 | AL59: ESEVERINO | AM59: SC EN APROBACION
A60: 55 | B60: OPS_054 | C60: OPS | D60: Freddy Valderrama | H60: Parra 1 - Patio San Isidro - Elevador para discapacitados | I60: Plataforma para que discapacitados tengan acceso al patio San Isidro | J60: 15,Parra 1 - Patio San Isidro - Elevador para discapacitados,mp4 | K60: OK | L60: =SUM(M60:O60) -> 13 | M60: 5 | N60: 5 | O60: 3 | P60: OK para evaluar en función a la evacuación | Q60: SI | R60: UTP Arequipa | S60: 70110103 | T60: UTP PARRA 201-203 - AREQUIPA | U60: 100000 | W60: A | X60: 46235 | Y60: 46325 | AB60: EN PROCESO | AD60: Infraestructura
A61: 56 | B61: OPS_055 | C61: OPS | D61: Elmer Raul ILLANES PAUCAR | F61: eillanes@utp,edu,pe | G61: 994 690 404 | H61: Parra 1 - Estacionamientos - 02 puntos de agua | I61: Habilibitar 1 punto de agua en estacionamientos de sótano 3 y 1 punto de agua en sótano 4 | J61: 08,Parra 2 - Estacionamientos - 02 puntos de agua,mp4 | K61: OK | L61: =SUM(M61:O61) -> 7 | M61: 1 | N61: 2 | O61: 4 | Q61: SI | R61: UTP Arequipa | S61: 70110107 | T61: UTP PARRA WASHINGT 217-219 AREQUIPA | U61: 6375.35 | V61: 6375.35 | W61: C | X61: 46143 | Y61: 46203 | Z61: 46082 | AA61: 46162 | AB61: EJECUTADO | AC61: EJECUTADO | AD61: Mantenimiento | AE61: SC-0000118387-2026 | AF61: 46078 | AG61: OC-0000128327-2026 | AH61: 46141 | AI61: MEJ00210 | AJ61: UTP_Parra 2 _Estacionamientos_02 puntos de agua | AK61: 46055 | AL61: ESEVERINO
A62: 57 | B62: OPS_056 | C62: OPS | D62: Eloy Pocohuanca | F62: epocohuanc@utp,edu,pe | G62: 937 029 622 | H62: Proyecto de estandarización de cafeterías | Q62: SI | R62: UTP Huancayo | S62: 70190101 | T62: UTP AV,CIRCUNVALACIÓN 449 - HUANCAYO | U62: 27000 | V62: 15871.978 | W62: B | X62: 46174 | Y62: 46295 | Z62: 46174 | AB62: EN PROCESO | AD62: Proyectos Ops | AE62: SC-0000126648-2026 / SC-0000126650-2026/SC-0000140266-2026 | AF62: 46147 | AG62: OC-0000133495-2026 / OC-0000135467-2026/ OC-0000142569-2026 | AH62: 04/06 / 15/06 04/08 | AI62: PROY1384 | AJ62: UTP_Hcyo_Proyecto_estandarizacion_cafeterias | AK62: 46055 | AL62: ESEVERINO | AM62: SC-0000126650-2026 (GENERICO) / NR OC-0000133495-2026 enviado/NR ENVIADA OC-0000142569-2026/OC-0000135467-2026 NR ENVIADA
A63: 58 | B63: OPS_057 | C63: OPS | D63: Eloy Pocohuanca | F63: epocohuanc@utp,edu,pe | G63: 937 029 622 | H63: Proyecto de estandarización de cafeterías | Q63: SI | R63: UTP Ica | S63: 70160101 | T63: UTP SUB EUB-5 SAN JOSE - ICA | U63: 27000 | V63: 30853.03 | W63: B | X63: 46174 | Y63: 46295 | Z63: 46174 | AB63: EN PROCESO | AD63: Proyectos Ops | AE63: SC-0000126648-2026 / SC-0000126649-2026 / SC-0000126650-2026 / SC-0000140260-2026 | AF63: 46147 | AG63: OC-0000132200-2026 / OC-0000132404-2026 /OC-0000133495-2026/OC-0000137135-2026/OC-0000142573-2026 | AH63: 25/05 / 27/05 / 04/06 /25/06 04/08 | AI63: PROY1385 | AJ63: UTP_Ica_Proyecto_estandarizacion_cafeterias | AK63: 46055 | AL63: ESEVERINO | AM63: SC-0000126650-2026 - SC-0000126648-2026 ( GENERICO) (OC-0000137135-2026 AM000974) / NR enviada: OC-0000132404-2026/ NR enviada OC-0000142538-2026 /NR ENVIADA OC-0000142573-2026/NR ENVIADA OC-0000137135-2026
A64: 59 | B64: OPS_058 | C64: OPS | D64: Eloy Pocohuanca | F64: epocohuanc@utp,edu,pe | G64: 937 029 622 | H64: Proyecto de estandarización de cafeterías | Q64: SI | R64: UTP Trujillo | S64: 70180103 | T64: UTP NICOLAS PIEROLA - TRUJILLO | U64: 27000 | V64: 14434.021 | W64: B | X64: 46113 | Y64: 46264 | Z64: 46174 | AB64: EJECUTADO | AD64: Proyectos Ops | AE64: SC-0000126648-2026 / SC-0000126650-2026 / SC-0000138448-2026/SC-0000143980-2026 | AF64: 05/05 09/09 | AG64: OC-0000133495-2026 / OC-0000135468-2026 / OC-0000142575-2026 | AH64: 04/06 / 15/06 04/08 | AI64: PROY1386 | AJ64: UTP_Trujillo_Proyecto_estandarizacion_cafeterias | AK64: 46055 | AL64: ESEVERINO | AM64: SC-0000126650-2026 (GENERICO) / NR OC-0000133495-2026 enviado/ NR OC-0000142538-2026 ENVIADA/ NR OC-0000135468-2026 ENVIADA/OC-0000142575-2026 TIENE NR
A65: 60 | B65: OPS_059 | C65: OPS | D65: Eloy Pocohuanca | F65: epocohuanc@utp,edu,pe | G65: 937 029 622 | H65: Proyecto de estandarización de cafeterías | Q65: SI | R65: UTP Chimbote | S65: 70150101 | T65: UTP PASERO DEL MAR MZ C9- LT2 - CHIMBOTE | U65: 27000 | V65: 2799.9984 | W65: B | X65: 46113 | Y65: 46264 | Z65: 46174 | AB65: EJECUTADO | AD65: Proyectos Ops | AE65: SC-0000126648-2026 / SC-0000126650-2026 | AF65: 46147 | AG65: OC-0000133495-2026 / OC-0000135466-2026/OC-0000142565-2026 | AH65: 04/06 / 15/06 / 08/04 | AI65: PROY1387 | AJ65: UTP_Chimbote_Proyecto_estandarizacion_cafeterias | AK65: 46055 | AL65: ESEVERINO | AM65: SC-0000126650-2026 ( GENERICO) / NR OC-0000133495-2026 enviado/OC-0000142565-2026 TIENE NR/
A66: 61 | B66: OPS_060 | C66: OPS | D66: Eloy Pocohuanca | F66: epocohuanc@utp,edu,pe | G66: 937 029 622 | H66: Proyecto de implementación de áreas de esparcimiento III Etapa | Q66: SI | R66: UTP Piura | S66: 70170101 | T66: UTP AV,PANAMERICANA 234 -PIURA | U66: 37500 | V66: 37500 | W66: B | X66: 46174 | Y66: 46265 | Z66: 46203 | AB66: EJECUTADO | AD66: Proyectos Ops | AE66: SC-0000134265-2026 / SC-0000134267-2026 /SC-0000134318-2026 /SC-0000135915-2026 | AF66: 22/06 / 24/06 | AG66: OC-0000136955-2026/OC-0000141560-2026 | AH66: 46197 | AI66: PROY1388 | AJ66: UTP_Piura_Implementacion_areas esparcimiento_III Etapa | AK66: 46055 | AL66: ESEVERINO | AM66: En proceso de diseño con Jossi/OC-0000136955-2026 TIENE NR/ | AO66: REVISAR PRESUPUESTO
A67: 62 | B67: OPS_061 | C67: OPS | D67: Eloy Pocohuanca | F67: epocohuanc@utp,edu,pe | G67: 937 029 622 | H67: Proyecto de implementación de áreas de esparcimiento III Etapa | Q67: SI | R67: UTP Chiclayo | S67: 70120201 | T67: UTP AV, PROGRESO CON AV, EVITAMIENTO S/N - CHICLAYO | U67: 37500 | V67: 37500 | W67: B | X67: 46174 | Y67: 46265 | AB67: EJECUTADO | AD67: Proyectos Ops | AE67: SC-0000133361-2026 | AF67: 46192 | AI67: PROY1389 | AJ67: UTP_Chiclayo_Implementacion_areas esparcimiento_III Etapa | AK67: 46055 | AL67: ESEVERINO | AM67: En proceso de diseño con Jossi
A68: 63 | B68: OPS_062 | C68: OPS | D68: Eloy Pocohuanca | F68: epocohuanc@utp,edu,pe | G68: 937 029 622 | H68: Proyecto de implementación de áreas de esparcimiento III Etapa | Q68: SI | R68: UTP Ica | S68: 70160101 | T68: UTP SUB EUB-5 SAN JOSE - ICA | U68: 37500 | V68: 8399.9952 | W68: B | X68: 46174 | Y68: 46265 | AB68: EJECUTADO | AD68: Proyectos Ops | AE68: SC-0000140219-2026/ SC-0000136124-2026/SC-0000140219-2026 | AF68: 12/08 04/08 12/09 | AG68: OC-0000142538-2026 | AH68: 46238 | AI68: PROY1390 | AJ68: UTP_Ica_Implementacion_areas esparcimiento_III Etapa | AK68: 46055 | AL68: ESEVERINO | AM68: En proceso de diseño con Jossi/ LA SC-0000136124-2026 YA TIENE NR
A69: 64 | B69: OPS_063 | C69: OPS | D69: Eloy Pocohuanca | F69: epocohuanc@utp,edu,pe | G69: 937 029 622 | H69: Proyecto de implementación de áreas de esparcimiento III Etapa | Q69: SI | R69: UTP Trujillo | S69: 70180103 | T69: UTP NICOLAS PIEROLA - TRUJILLO | U69: 37500 | V69: 37500 | W69: B | X69: 46174 | Y69: 46265 | AB69: EJECUTADO | AD69: Proyectos Ops | AE69: SC-0000136125-2026 | AF69: 46209 | AG69: OC-0000141554-2026 / OC-0000141566-2026 | AH69: 46228 | AI69: PROY1391 | AJ69: UTP_Trujillo_Implementacion_areas esparcimiento_III Etapa | AK69: 46055 | AL69: ESEVERINO | AM69: En proceso de diseño con Jossi
A70: 65 | B70: OPS_064 | C70: OPS | D70: VICENTE CAYETANO RODRIGUEZ PASTOR | F70: eillanes@utp,edu,pe | G70: 994 690 404 | H70: Proyecto de implementación de filtro de armónico | J70: Parra 2 - Fachada,pdf | K70: OK | L70: =SUM(M70:O70) -> 10 | M70: 2 | N70: 5 | O70: 3 | Q70: SI | R70: UTP Chiclayo | S70: 70120201 | T70: UTP AV, PROGRESO CON AV, EVITAMIENTO S/N - CHICLAYO | U70: 87000 | W70: A | AB70: CANCELADO | AD70: Mantenimiento | AI70: PROY1392 | AJ70: UTP_Chiclayo_Implementacion_filtro armonico | AK70: 46055 | AL70: ESEVERINO | AM70: NO SE CANCELA PASA AL PRESUPUESTO DE LUMINARIAS 2025 | AO70: SE EJECIUTA PTO 2025 | AP70: ADICIONAL
A71: 66 | B71: OPS_065 | C71: OPS | D71: VICENTE CAYETANO RODRIGUEZ PASTOR | F71: eillanes@utp,edu,pe | G71: 994 690 404 | H71: Proyecto Implementacion de filtro de armonico Ica | Q71: SI | R71: UTP Ica | S71: 70160101 | T71: UTP SUB EUB-5 SAN JOSE - ICA | U71: 87000 | W71: B | AB71: CANCELADO | AD71: Mantenimiento | AI71: PROY1393 | AJ71: UTP_Ica_Implementacion_filtro armonico | AK71: 46055 | AL71: ESEVERINO | AM71: NO SE CANCELA PASA AL PRESUPUESTO DE LUMINARIAS 2025 | AO71: SE EJECIUTA PTO 2025 | AP71: ADICIONAL
A72: 67 | B72: OPS_066 | C72: OPS | D72: VICENTE CAYETANO RODRIGUEZ PASTOR | F72: eillanes@utp,edu,pe | G72: 994 690 404 | H72: Proyecto Implementacion de filtro de armonico Tacna y Arica | Q72: SI | R72: UTP Arequipa | S72: 70110101 | T72: UTP TACNA-ARICA 158-160-162 - AREQUIPA | U72: 87000 | W72: B | AB72: CANCELADO | AD72: Mantenimiento | AI72: PROY1394 | AJ72: UTP_Parra 2_Implementacion_filtro armonico | AK72: 46055 | AL72: ESEVERINO | AM72: NO SE CANCELA PASA AL PRESUPUESTO DE LUMINARIAS 2025 | AO72: SE EJECIUTA PTO 2025 | AP72: ADICIONAL
A73: 68 | B73: OPS_067 | C73: OPS | D73: Eloy /Gustavo | H73: Reestructuracion de espacios en cochera para motos y bicicletas | I73: Actualmente tenemos un ambiente desordenado (motos carros y bicicletas estacionan en todos lados) esto genera problemas de rayaduras saturación de espacios bloqueo de espacios de automóviles por bicicletas y motos), | J73: https://www,dropbox,com/scl/fo/oeaqdfv6av0j9jb28hmao/ALECckvrfXoqZnYvtw5pvYQ?rlkey=2vmcdlnqb4hnr1yli9uuq9jy4&st=juylf8sd&dl=0 | K73: OK | L73: =SUM(M73:O73) -> 10 | M73: 4 | N73: 2 | O73: 4 | Q73: SI | R73: UTP Ica | S73: 70160101 | T73: UTP SUB EUB-5 SAN JOSE - ICA | U73: 5000 | W73: A | X73: 46174 | Y73: 46310 | AB73: EN PROCESO | AD73: Proyectos Ops / Mantenimiento | AE73: SC-0000120475-2026 | AF73: 46094 | AG73: SC DEVUELTA | AI73: PROY1395 | AJ73: UTP_Ica_Reestructuracion _espacios _cochera_motos y bicicletas | AK73: 46055 | AL73: ESEVERINO | AM73: SC DEVUELTA se cambiará alcance
A74: 69 | B74: OPS_068 | C74: OPS | D74: IRENE JAEN | H74: Rehabilitación de las veredas del perímetro principal del campus universitario | I74: La intervención mejorará la seguridad peatonal y la accesibilidad reduciendo riesgos de accidentes y mejorando la imagen institucional | J74: https://utpedupe,sharepoint,com/:f:/s/OperacionesCIX/EqUcK-qj9o9BhUnp4BxLFEkB4WPvvSS9VeygGf_9Z8t1Fw?e=92zjI3 | K74: OK | L74: =SUM(M74:O74) -> 11 | M74: 4 | N74: 4 | O74: 3 | P74: No podemos intervenir en la vía publica sería una iniciativa a trabajar con la municipalidd distrital/provincial, Presupuesto insuficiente | Q74: SI | R74: UTP Chiclayo | S74: 70120201 | T74: UTP AV, PROGRESO CON AV, EVITAMIENTO S/N - CHICLAYO | U74: 16000 | W74: A | X74: 46235 | Y74: 46356 | AB74: PENDIENTE | AD74: Infraestructura
A75: 70 | B75: OPS_069 | C75: OPS | D75: Randall Castillo | H75: Remodelación de baños de los pisos 2,3 4 y 5 de Sede Central (PISO 6 CLAUSURADO Y PISO 1 YA CUENTA CON ESTANDAR) | I75: Remodelar mayólicas urinarios inodoros griferías y puertas de 10 baños de hombres y 10 de mujeres de los pisos 234 y 5, PISO 1 YA CUENTA CON BAÑOS REMODELADOS Y PISO 6 CLAUSURADO, La infraestructura en los baños requiere una renovación completa, Son baños que no han sido remodelados en por lo menos 20 años, Esto impacta negativamente en la percepción de los alumnos sobre la sede, | J75: https://drive,google,com/drive/folders/1kgZDIy-N2hSe5LTIEDs3SxsFwzpNrirb | K75: OK | L75: =SUM(M75:O75) -> 13 | M75: 5 | N75: 5 | O75: 3 | P75: Con una ejecución de S/, 570 K (Ver PROY 1053) solo se pudo remodelar dos pisos de baños si el alcance es remodelar todos los pisos se debe pedir aprobación por lo menos de S/, 2MM | Q75: SI | R75: UTP Lima Centro | S75: 10110201 | T75: UTP PETITTHOURS 116 - LIMA | U75: 500000 | W75: A | X75: 46235 | Y75: 46356 | AB75: EN PROCESO | AD75: Infraestructura | AO75: cancelado | AP75: REVISAR
A76: 71 | B76: OPS_070 | C76: OPS | D76: Randall Castillo | H76: Remodelación de baños de todos los pisos de la sede Pacífico | I76: Remodelar mayólicas urinarios inodoros griferías y puertas de 6 baños de hombres y 6 de mujeres, La infraestructura en los baños requiere una renovación completa, Son baños que no han sido remodelados en por lo menos 20 años, Esto impacta negativamente en la percepción de los alumnos sobre la sede, | J76: https://utpedupe-my,sharepoint,com/:f:/g/personal/gricaza_utp_edu_pe/EpafVnJ5BdxEoPIvXq4Pu34BBViXn95F5XlpW2wVwugdBQ?e=v7ftsH | K76: OK | L76: =SUM(M76:O76) -> 13 | M76: 5 | N76: 5 | O76: 3 | P76: Con una ejecución de S/, 570 K solo se pudo remodelar dos pisos de baños si el alcance es remodelar todos los pisos se debe pedir aprobación por lo menos de S/, 1,8 MM | Q76: SI | R76: UTP Lima Centro | S76: 10110102 | T76: UTP AREQUIPA 660- 670 - LIMA | U76: 300000 | W76: A | X76: 46235 | Y76: 46304 | AB76: PENDIENTE | AD76: Infraestructura | AM76: Pendiente en consulta
A77: 72 | B77: OPS_071 | C77: OPS | D77: Eloy / Raul | H77: Remodelacion de oficina de soporte TI | I77: Remodelacion ambiente (retiro pared dry wall y resanar) | J77: https://utpedupe,sharepoint,com/:f:/s/OperacionesCIX/Essg4D4TQX1LmAJFzksgG6kBnlhTXLK39MiNGY3rPfq0hA?e=FBnYNq | K77: OK | L77: =SUM(M77:O77) -> 9 | M77: 1 | N77: 3 | O77: 5 | Q77: SI | R77: UTP Chiclayo | S77: 70120201 | T77: UTP AV, PROGRESO CON AV, EVITAMIENTO S/N - CHICLAYO | U77: 7500 | V77: 3156.24 | W77: B | X77: 46082 | Y77: 46082 | Z77: 46082 | AA77: 46111 | AB77: EJECUTADO | AC77: EJECUTADO | AD77: Proyectos Ops / Mantenimiento | AE77: SC-0000116652-2026 | AF77: 46062 | AG77: OC-0000121741-2026 | AH77: 46076 | AI77: PROY1396 | AJ77: UTP_Chiclayo_Remodelacion_oficina_soporte TI | AK77: 46055 | AL77: ESEVERINO
A78: 73 | B78: OPS_072 | C78: OPS | D78: Eloy / Raul | H78: Remodelacion de punto de acopio | I78: La remodelación del punto de acopio mejorará la organización seguridad y eficiencia en el manejo y almacenamiento de materiales peligrosos | J78: https://utpedupe,sharepoint,com/:f:/s/OperacionesCIX/Elk3R8GCqBFDmAjzU0eGqSYBXXeQCM-ydsZIN07e3BqYuQ?e=j8T29G | K78: OK | L78: =SUM(M78:O78) -> 9 | M78: 2 | N78: 3 | O78: 4 | Q78: SI | R78: UTP Chiclayo | S78: 70120201 | T78: UTP AV, PROGRESO CON AV, EVITAMIENTO S/N - CHICLAYO | U78: 7500 | V78: 16040.18 | W78: B | X78: 46082 | Y78: 46082 | Z78: 46082 | AA78: 46111 | AB78: EJECUTADO | AC78: EJECUTADO | AD78: Proyectos Ops / Mantenimiento | AE78: SC-0000116654-2026 | AF78: 46062 | AG78: OC-0000122239-2026 | AH78: 46080 | AI78: PROY1397 | AJ78: UTP_Chiclayo_Remodelacion_punto de acopio | AK78: 46055 | AL78: ESEVERINO
A79: 74 | B79: OPS_073 | C79: OPS | D79: Katherine Polo | H79: REMODELACION DEL FONDO DE ESCENARIO EN AUDITORIOS ( TTA SC Pacífico) | J79: REMODELACION ESCENARIOS AUDITORIOS 2026 | Q79: SI | R79: UTP Lima Centro | S79: 10110205 | T79: UTP AV, AREQUIPA 265-279 - LIMA | U79: 50000 | V79: 42050.95 | W79: A | X79: 46235 | Y79: 46234 | AB79: EJECUTADO | AD79: Infraestructura | AI79: PROY1432
A80: 75 | B80: OPS_074 | C80: OPS | D80: Katherine Polo | H80: REMODELACION DEL FONDO DE ESCENARIO EN AUDITORIOS ( TTA SC Pacífico) | J80: REMODELACION ESCENARIOS AUDITORIOS 2026 | Q80: SI | R80: UTP Lima Centro | S80: 10110201 | T80: UTP PETITTHOURS 116 - LIMA | U80: 50000 | V80: 47954.78 | W80: A | X80: 46235 | Y80: 46234 | AB80: EJECUTADO | AD80: Infraestructura | AI80: PROY1430
A81: 76 | B81: OPS_075 | C81: OPS | D81: Katherine Polo | F81: mailto:eillanes@utp.edu.pe | H81: REMODELACION DEL FONDO DE ESCENARIO EN AUDITORIOS ( TTA SC Pacífico) | I81: Las más críticas son TTA SC y Pacífico no cumplen con ningún estandar, LE LS SJL LN tienen estandar anterior en buena condición | J81: REMODELACION ESCENARIOS AUDITORIOS 2026 | K81: OK | L81: =SUM(M81:O81) -> 11 | M81: 5 | N81: 5 | O81: 1 | P81: OK | Q81: SI | R81: UTP Lima Centro | S81: 10110102 | T81: UTP AREQUIPA 660- 670 - LIMA | U81: 50000 | V81: 27769.98 | W81: A | X81: 46235 | Y81: 46234 | AB81: EJECUTADO | AD81: Infraestructura | AI81: PROY1431 | AM81: Pendiente en consulta
A82: 77 | B82: OPS_076 | C82: OPS | D82: Vicente Rodríguez/Eloy | F82: mailto:eillanes@utp.edu.pe | H82: REMODELACION LAB, MAQUINAS ELECTRICAS | Q82: SI | R82: UTP Lima Sur | S82: 10220106 | T82: UTP EL TRIUNFO S/N-VILLA SALVA - LIMA | U82: 18000 | V82: 15955.15 | W82: A | X82: 46082 | Y82: 46111 | Z82: 46082 | AA82: 46111 | AB82: EJECUTADO | AC82: EJECUTADO | AD82: Proyectos Ops / Mantenimiento | AE82: SC-0000116737-2026 | AF82: 46063 | AG82: OC-0000122075-2026 | AH82: 46079 | AI82: PROY1398 | AJ82: UTP_VES_REMODELACION_ LAB, MAQUINAS ELECTRICAS | AK82: 46055 | AL82: ESEVERINO
A83: 78 | B83: OPS_077 | C83: OPS | D83: Elmer Raul ILLANES PAUCAR | F83: eillanes@utp,edu,pe | G83: 994 690 404 | H83: Renovación de 40 puertas deterioradas | I83: Renovacion de puertas deterioradas por uso | J83: https://utpedupe,sharepoint,com/:f:/s/OperacionesCIX/Ekv9RKVnw6FInLOkchvl56kBhs3dV1bLiOEZkNNwlTbHkQ?e=ir6xIq | K83: OK | L83: =SUM(M83:O83) -> 12 | M83: 4 | N83: 4 | O83: 4 | Q83: SI | R83: UTP Chiclayo | S83: 70120201 | T83: UTP AV, PROGRESO CON AV, EVITAMIENTO S/N - CHICLAYO | U83: 64000 | V83: 80868.7 | W83: A | X83: 46113 | Y83: 46203 | Z83: 46113 | AA83: 46162 | AB83: EJECUTADO | AC83: EJECUTADO | AD83: Mantenimiento | AE83: SC-0000116991-2026 | AF83: 46064 | AG83: OC-0000121764-2026 | AH83: 46090 | AI83: PROY1399 | AJ83: UTP_Chiclayo_Renovación_40 puertas deterioradas | AK83: 46055 | AL83: ESEVERINO | AM83: solicitante Maria Gonzales
A84: 79 | B84: OPS_078 | C84: OPS | D84: VICENTE CAYETANO RODRIGUEZ PASTOR | F84: vrodriguep@utp,edu,pe | G84: 955 141 444 | H84: Renovación de 70 griferías de lavatorios de los baños en Torre Arequipa | I84: Las griferías de los lavatorios con más de 10 años de uso han superado su vida útil y presentan fallas recurrentes que afectan su operatividad, Su renovación mejorará la funcionalidad reducirá costos de mantenimiento y reforzará la imagen institucional, 70 unidades de grifería en los baños que requieren renovación | J84: https://drive,google,com/file/d/1JYwl9pdZ1_zDv2cv1nn5kBfJq9di6w6U/view?usp=drive_link | K84: OK | L84: =SUM(M84:O84) -> 8 | M84: 2 | N84: 5 | O84: 1 | Q84: SI | R84: UTP Lima Centro | S84: 10110205 | T84: UTP AV, AREQUIPA 265-279 - LIMA | U84: 0 | V84: 0 | W84: C | AB84: CANCELADO | AD84: Mantenimiento | AI84: PROY1400 | AJ84: UTP_Arq265-279_Renovación_70 griferías_lavatorios_baños_Torre II | AK84: 46055 | AL84: ESEVERINO | AM84: Se cancela revisado y aprobado por Elida (SC-0000116744-2026) | AO84: CANCELADO
A85: 80 | B85: OPS_079 | C85: OPS | D85: VICENTE CAYETANO RODRIGUEZ PASTOR | F85: vrodriguep@utp,edu,pe | G85: 955 141 444 | H85: Renovación de 77 fluxómetros de los baños en Torre Arequipa | I85: Se requiere la renovación de los fluxómetros de los baños por tiempo de vida estan muy desgastados y ya no funcionan correctamente inclusive con los mantenimiento correspondientes, Lo que impacta a la limpieza e imagen hacia el alumno, Asimismo los piso del 1 al 5 son los más transitados , Son 77 fluxómetros que requieren renovación, | J85: https://drive,google,com/file/d/14iwmsQ7khk8EqBjZ5JCRthmcgOJr87ki/view?usp=drive_link | K85: OK | L85: =SUM(M85:O85) -> 8 | M85: 2 | N85: 5 | O85: 1 | Q85: SI | R85: UTP Lima Centro | S85: 10110205 | T85: UTP AV, AREQUIPA 265-279 - LIMA | U85: 59000 | V85: 23151.13 | W85: C | X85: 46082 | Y85: 46203 | Z85: 46082 | AA85: 46167 | AB85: EJECUTADO | AC85: EJECUTADO | AD85: Mantenimiento | AE85: SC-0000116775-2026 / SC-0000119671-2026 | AF85: 10/02 / 09/03 | AG85: OC-0000123026-2026 / OC-0000123222-2026 | AH85: 07/03 / 10/03 | AI85: PROY1401 | AJ85: UTP_Arq265-279_Renovación_77 fluxómetros_baños_Torre II | AK85: 46055 | AL85: ESEVERINO
A86: 81 | B86: OPS_080 | C86: OPS | D86: Eloy Pocohuanca | F86: epocohuanc@utp,edu,pe | G86: 937 029 622 | H86: Renovación de mobiliario de biblioteca de la sede Pacifico | I86: Renovación de mobiliario 8 mesas 72 sillas pintado de ambiente y counter e instalación de luces led, El mobiliariono no corresponde al estandar de bibliotecas, | J86: https://utpedupe-my,sharepoint,com/:f:/g/personal/gricaza_utp_edu_pe/El5xox1oxXdOmgK68SuRThgB5LSa__eCpJCarXL9XzhewA?e=iWdBTX | K86: OK | L86: =SUM(M86:O86) -> 12 | M86: 5 | N86: 5 | O86: 2 | Q86: SI | R86: UTP Lima Centro | S86: 10110102 | T86: UTP AREQUIPA 660- 670 - LIMA | U86: 20000 | V86: 15064.89 | W86: A | X86: 46188 | Y86: 46310 | Z86: 46203 | AB86: EN PROCESO | AD86: Proyectos Ops / Campus | AE86: SC-0000130128-2026 / SC-0000130143-2026 | AF86: 46168 | AG86: OC-0000132339-2026 / OC-0000135868-2026 | AH86: 26/05 / 18/06 | AI86: AM001201 | AJ86: UTP_Arq660-670_Renovación_mobiliario_biblioteca/OC-0000135868-2026 YA TIENE NR | AK86: 46055 | AL86: ESEVERINO | AM86: Pendiente diseño de mesa con tomacorrientes
A87: 82 | B87: OPS_081 | C87: OPS | D87: Eloy Pocohuanca/Carlos Sanchez | F87: epocohuanc@utp,edu,pe | G87: 937 029 622 | H87: RENOVACION DE MOBILIARIO EQUIPOS ALFOMBRA DE AUDITORIO (SJL) | J87: RENOVACION MOBILIARIO ALFOMBRA AUDITORIOS | Q87: SI | R87: UTP SJL | S87: 10220110 | T87: UTP AV,SOL SUB LT 13B MZG SJL - LIMA | U87: 98500 | W87: A | X87: 46174 | Y87: 46295 | AB87: EN PROCESO | AD87: Proyectos Ops / Campus | AE87: SC-0000141274-2026 | AF87: 46254 | AI87: AM001202 | AJ87: UTP_SJL_RENOVACION DE MOBILIARIO EQUIPOS ALFOMBRA DE AUDITORIO (SJL Pacífico) | AK87: 46055 | AL87: ESEVERINO | AM87: Definir alcance Grecia
A88: 83 | B88: OPS_082 | C88: OPS | D88: Eloy Pocohuanca/Carlos Sanchez | F88: epocohuanc@utp,edu,pe | G88: 937 029 622 | H88: RENOVACION DE MOBILIARIO EQUIPOS ALFOMBRA DE AUDITORIO ( Pacífico) | I88: SJL (140K): CAMBIO DE ALFOMBRA SILLAS Y PARLANTES POR DETERIORO COLOCAR CONSOLA DIGITAL, COLOCAR ECRAN MAS GRANDE MEDIDAS APROX 3 mt ancho X 2,5 mt alto, MEJORAR ILUMINACIÓN LED PARA ÁREA DE PÚBLICO Y LED GRADUABLE EN ESCENARIO CONTROL DESDE CONSOLA LIJADO Y PINTADO DE PISO DE ESTRADO PACIFICO (57K): actualización del mobiliario 100 sillas atril nuevo pintado de paredes y cambio de alfombra, Considerar el tema acustico para evitar filtración sonora | J88: RENOVACION MOBILIARIO ALFOMBRA AUDITORIOS | K88: OK | L88: =SUM(M88:O88) -> 11 | M88: 5 | N88: 5 | O88: 1 | Q88: SI | R88: UTP Lima Centro | S88: 10110102 | T88: UTP AREQUIPA 660- 670 - LIMA | U88: 98500 | V88: 78800.161 | W88: A | X88: 46174 | Y88: 46310 | Z88: 46137 | AB88: EN PROCESO | AD88: Proyectos Ops / Campus | AE88: SC-0000124574-2026 / SC-0000137824-2026 | AF88: 46132 | AG88: OC-0000128967-2026 / OC-0000131424-2026 / OC-0000138255-2026 | AH88: 06/05 / 22/05 / 02/07 | AI88: AM001203 | AJ88: UTP_Arq660-670_RENOVACION DE MOBILIARIO EQUIPOS ALFOMBRA DE AUDITORIO (SJL Pacífico) | AK88: 46055 | AL88: ESEVERINO | AM88: OC-0000128967-2026 (AUDIO) EJECUTADO / SC-0000137824-2026(pintura)/OC-0000131424-2026 TIENE NR/OC-0000138255-2026 TIENE NR
A89: 84 | B89: OPS_083 | C89: OPS | D89: Gustavo Mallaupoma | H89: Renovación de piso en la ruta de salida de los estudiantes (Av Petit Thouars) de Sede Central | I89: El piso se encuentra desgastado pese a que se le da tratamiento el efecto no es permanente ni duradero, Así mismo tiene desniveles que en época de lluvias forman charcos que pueden provocar accidentes, Genera una imagen negativa para la percepción de los estudiantes, | J89: https://drive,google,com/drive/folders/1nl6Zmy9Fa9oSNtlbJ6UyGcux8kj_OhHc | K89: OK | L89: =SUM(M89:O89) -> 9 | M89: 3 | N89: 5 | O89: 1 | Q89: SI | R89: UTP Lima Centro | S89: 10110201 | T89: UTP PETITTHOURS 116 - LIMA | U89: 30000 | V89: 9779.77 | W89: B | X89: 46082 | Y89: 46082 | Z89: 46082 | AA89: 46111 | AB89: EJECUTADO | AC89: EJECUTADO | AD89: Mantenimiento | AE89: SC-0000119911-2026 | AF89: 46091 | AG89: OC-0000124128-2026 | AH89: 46098 | AI89: PROY1402 | AJ89: UTP_PTT_116_Renovación de piso en la ruta de salida de los estudiantes | AK89: 46055 | AL89: ESEVERINO | AM89: Consultar con Fredy
A90: 85 | B90: OPS_084 | C90: OPS | D90: Gustavo Mallaupoma | H90: Renovación de piso en la ruta de salida de los estudiantes (Av Hernán Velarde) de Sede Central | I90: El piso se encuentra desgastado pese a que se le da tratamiento el efecto no es permanente ni duradero, Así mismo tiene desniveles que en época de lluvias forman charcos que pueden provocar accidentes, Genera una imagen negativa para la percepción de los estudiantes, | J90: https://drive,google,com/drive/folders/1wblKsN_IB2rV3gYmxJP5T8ffk2R6W2f5?usp=drive_link | K90: OK | L90: =SUM(M90:O90) -> 9 | M90: 3 | N90: 5 | O90: 1 | Q90: SI | R90: UTP Lima Centro | S90: 10110201 | T90: UTP PETITTHOURS 116 - LIMA | U90: 30000 | V90: 22497.76 | W90: B | X90: 46082 | Y90: 46082 | Z90: 46082 | AA90: 46111 | AB90: EJECUTADO | AC90: EJECUTADO | AD90: Mantenimiento | AE90: SC-0000119915-2026 | AF90: 46091 | AG90: OC-0000124209-2026 | AH90: 46099 | AI90: PROY1403 | AJ90: UTP_Hernan Velarde _Renovación de piso en la ruta de salida de los estudiantes | AK90: 46055 | AL90: ESEVERINO | AM90: Consultar con Fredy
A91: 86 | B91: OPS_085 | C91: OPS | D91: Gustavo Mallaupoma | H91: Reprogramación de ascensores por pisos | I91: Se propone la reprogramación de los ascensores asignando a cada uno un rango específico de pisos, Con esta medida buscamos optimizar su uso reducir los tiempos de espera y evitar aglomeraciones tal como ya se viene aplicando con éxito en otros campus, | J91: Proyectos CAPEX_PIURA - Dropbox | K91: OK | L91: =SUM(M91:O91) -> 13 | M91: 5 | N91: 4 | O91: 4 | Q91: SI | R91: UTP Piura | S91: 70170101 | T91: UTP AV,PANAMERICANA 234 -PIURA | U91: 50000 | W91: A | X91: 46233 | Y91: 46310 | AB91: EN PROCESO | AD91: Mantenimiento | AE91: SC-0000116872-2026 | AF91: 46063 | AG91: OC-0000142661-2026 | AH91: 46239 | AI91: PROY1404 | AJ91: UTP_Piura_Reprogramación de ascensores por pisos | AK91: 46055 | AL91: ESEVERINO | AM91: Se volvió a enviar la solicitud de nuevo encargado Gustavo M.
A92: 87 | B92: OPS_086 | C92: OPS | D92: Alberto Fajardo Corpancho | F92: jfajardo@utp,edu,pe | G92: 960 961 878 | H92: Sistema fotoeléctrico/Reinstalación_Pacífico | Q92: SI | R92: UTP Lima Centro | S92: 10110102 | T92: UTP AREQUIPA 660- 670 - LIMA | U92: 7000 | V92: 6329.3 | W92: A | X92: 46082 | Y92: 46264 | Z92: 46082 | AB92: EJECUTADO | AD92: Seguridad | AE92: SC-0000116881-2026 | AF92: 46063 | AG92: OC-0000121706-2026 | AH92: 46076 | AI92: PROY1405 | AJ92: UTP_Arq660-670_Sistema fotoeléctrico | AK92: 46055 | AL92: ESEVERINO | AM92: Registrado
A93: 88 | B93: OPS_087 | C93: OPS | D93: Alberto Fajardo Corpancho | F93: jfajardo@utp,edu,pe | G93: 960 961 878 | H93: Sistema fotoeléctrico_Natalio Sanchez | Q93: SI | R93: Corporativo - Natalio | S93: 10110101 | T93: UTP NATALIO SANCHEZ 125 - LIMA | U93: 8964.8 | V93: 18495.13 | W93: A | X93: 46082 | Y93: 46172 | Z93: 46082 | AA93: 46157 | AB93: EJECUTADO | AC93: EJECUTADO | AD93: Seguridad | AE93: SC-0000117847-2026 | AF93: 46072 | AG93: OC-0000122664-2026 | AH93: 46085 | AI93: PROY1406 | AJ93: UTP_Nat Sanc125_Sistema fotoeléctrico | AK93: 46055 | AL93: ESEVERINO | AM93: NR ENVIADA POR SEG,
A94: 89 | B94: OPS_088 | C94: OPS | D94: Alberto Fajardo Corpancho | F94: jfajardo@utp,edu,pe | G94: 960 961 878 | H94: Cerco eléctrico_Torre Central | Q94: SI | R94: UTP Lima Centro | S94: 10110201 | T94: UTP PETITTHOURS 116 - LIMA | U94: 38303.5 | V94: 33424.94 | W94: A | X94: 46082 | Y94: 46172 | Z94: 46082 | AA94: 46157 | AB94: EJECUTADO | AC94: EJECUTADO | AD94: Seguridad | AE94: SC-0000117850-2026 | AF94: 46072 | AG94: OC-0000122877-2026 | AH94: 46087 | AI94: PROY1407 | AJ94: UTP_PTT116_Sistema fotoeléctrico | AK94: 46055 | AL94: ESEVERINO | AM94: NR ENVIADA POR SEG,
A95: 90 | B95: OPS_089 | C95: OPS | D95: Alberto Fajardo Corpancho | F95: jfajardo@utp,edu,pe | G95: 960 961 878 | H95: Cerco eléctrico_Torre II | Q95: SI | R95: UTP Lima Centro | S95: 10110204 | T95: UTP PETIT THOU383-385-TORRE II - LIMA | U95: 17047.6 | V95: 11775.98 | W95: A | X95: 46082 | Y95: 46172 | Z95: 46082 | AA95: 46172 | AB95: EJECUTADO | AC95: EJECUTADO | AD95: Seguridad | AE95: SC-0000117858-2026 | AF95: 46072 | AG95: OC-0000122655-2026 | AH95: 46085 | AI95: PROY1408 | AJ95: UTP_PTT383-385_Sistema fotoeléctrico | AK95: 46055 | AL95: ESEVERINO | AM95: NR ENVIADA POR SEG,
A96: 91 | B96: OPS_090 | C96: OPS | D96: Alberto Fajardo Corpancho | F96: jfajardo@utp,edu,pe | G96: 960 961 878 | H96: Cerco eléctrico_Torre Tecnológica Arequipa | Q96: SI | R96: UTP Lima Centro | S96: 10110205 | T96: UTP AV, AREQUIPA 265-279 - LIMA | U96: 26041 | V96: 20389.8 | W96: A | X96: 46082 | Y96: 46172 | Z96: 46082 | AA96: 46172 | AB96: EJECUTADO | AC96: EJECUTADO | AD96: Seguridad | AE96: SC-0000117872-2026 | AF96: 46072 | AG96: OC-0000122691-2026 | AH96: 46085 | AI96: PROY1409 | AJ96: UTP_Arq265-279_Sistema fotoeléctrico | AK96: 46055 | AL96: ESEVERINO | AM96: NR ENVIADA POR SEG,
A97: 92 | B97: OPS_091 | C97: OPS | D97: IRENE JAEN | H97: Techo Para graderia de Polideportivo | I97: Protección contra el calor extremoprevención de insolación y mejorar la experiencia de nuestros estudiantes en el uso de las canchas y eventos deportivos | J97: https://utpedupe,sharepoint,com/:f:/s/OperacionesCIX/EltkQlZGy5JAvifqNVbigy8Bs2fi2mK7KopX8G1jYEUr1Q?e=QJl6a3 | K97: OK | L97: =SUM(M97:O97) -> 12 | M97: 4 | N97: 4 | O97: 4 | P97: OK para avaluar | Q97: SI | R97: UTP Chiclayo | S97: 70120201 | T97: UTP AV, PROGRESO CON AV, EVITAMIENTO S/N - CHICLAYO | U97: 55000 | W97: A | X97: 46235 | Y97: 46356 | AB97: PENDIENTE | AD97: Infraestructura
A98: 93 | B98: OPS_092 | C98: OPS | D98: Elmer Raul ILLANES PAUCAR | F98: eillanes@utp,edu,pe | G98: 994 690 404 | H98: Tomacorrientes Hall principal | I98: Implementacion de tomacorrientes en Hall principal para reducir riesgos de accidentes y los espacios sean más atractivos para estudiantes, | J98: https://utpedupe,sharepoint,com/:f:/s/OperacionesCIX/Em9GiDa8sMRCvvwY22M06JsBhfFUuetCoxBI4uXtOME5Cg?e=VHAA2R | K98: OK | L98: =SUM(M98:O98) -> 10 | M98: 4 | N98: 2 | O98: 4 | Q98: SI | R98: UTP Chiclayo | S98: 70120201 | T98: UTP AV, PROGRESO CON AV, EVITAMIENTO S/N - CHICLAYO | U98: 10000 | V98: 9052.83 | W98: A | X98: 46082 | Y98: 46082 | Z98: 46082 | AA98: 46111 | AB98: EJECUTADO | AC98: EJECUTADO | AD98: Mantenimiento | AE98: SC-0000116996-2026 | AF98: 46064 | AG98: OC-0000122087-2026 | AH98: 46079 | AI98: MEJ00211 | AJ98: UTP_Chiclayo_Tomacorrientes Hall principal | AK98: 46055 | AL98: ESEVERINO | AM98: SC registrada por Maria Gonzales
A99: 94 | B99: OPS_093 | C99: OPS | D99: Elmer Raul ILLANES PAUCAR | F99: eillanes@utp,edu,pe | G99: 994 690 404 | H99: TyA - Azotea - Cobertura y Estandarización espacios de esparcimiento para colaboradores | I99: Habilitar terraza con elevación de parapeto implementación de cobertura e implementar mobiliario de acuerdo a estándar nacional incluyendo puntos de carga | J99: 29,TyA - Azotea - Cobertura y Estandarización espacios de esparcimiento,mp4 | K99: OK | L99: =SUM(M99:O99) -> 10 | M99: 4 | N99: 3 | O99: 3 | Q99: SI | R99: UTP Arequipa | S99: 70110101 | T99: UTP TACNA-ARICA 158-160-162 - AREQUIPA | U99: 400000 | W99: A | AB99: CANCELADO | AD99: Mantenimiento | AI99: PROY1410 | AJ99: UTP_Arq_Tacna y Arica 158-160-162_Habilitar terraza_esparcimiento_colaboradores | AK99: 46055 | AL99: ESEVERINO | AM99: PARA CONSULTAR CON ELIDA
A100: 95 | B100: OPS_094 | C100: OPS | D100: Eloy / Raul | H100: TyA - Ingreso y Salida Vehicular - Cambio de sentido o sistema de puertas | I100: Puertas invaden la vía pública(veredas) la Municipalidad lo ha observado las puertas permanecen abiertas, | J100: 31,TyA - Ingreso y Salida Vehicular - Cambio de sentido o sistema de puertas,mp4 | K100: OK | L100: =SUM(M100:O100) -> 9 | M100: 1 | N100: 4 | O100: 4 | Q100: SI | R100: UTP Arequipa | S100: 70110101 | T100: UTP TACNA-ARICA 158-160-162 - AREQUIPA | U100: 40000 | V100: 36598.41 | W100: B | X100: 46113 | Y100: 46203 | Z100: 46113 | AA100: 46162 | AB100: EJECUTADO | AC100: EJECUTADO | AD100: Proyectos Ops / Mantenimiento | AE100: SC-0000116997-2026 | AF100: 46064 | AG100: OC-0000125363-2026 | AH100: 46122 | AI100: PROY1411 | AJ100: UTP_Arq Parra 2_TyA - Ingreso y Salida Vehicular - Cambio de sentido o sistema de puertas | AK100: 46055 | AL100: ESEVERINO | AM100: Solicitante Maria Gonzales
A101: 96 | B101: OPS_095 | C101: OPS | D101: Freddy Valderrama | H101: TyA - Protección de ventanas externas en lab especializados | I101: Instalación de protección en inox para garantizar seguridad pero permitir el abrir y cerrar ventanas (pueden ser alarmas y sensores) | J101: 26,TyA - Protección de ventanas externas en lab especializados,mp4 | K101: OK | L101: =SUM(M101:O101) -> 8 | M101: 2 | N101: 2 | O101: 4 | P101: OK a evaluar se debe tener cuidado contratamiento de fachada | Q101: SI | R101: UTP Arequipa | S101: 70110101 | T101: UTP TACNA-ARICA 158-160-162 - AREQUIPA | U101: 30000 | W101: C | X101: 46235 | Y101: 46325 | AB101: EN PROCESO | AD101: Infraestructura
...

Sheet TD
A1: ESTADO | B1: (Todas)
A3: # | B3: Meses (FECHA FIN PLANIFICADA)
A4: CAMPUS | B4: <1/03/2026 | C4: Mar | D4: Abr | E4: May | F4: Jun | G4: Jul | H4: Ago | I4: Set | J4: Oct | K4: Nov | L4: Dic | M4: Total general
A5: UTP SJL | B5: =COUNTIFS(BD_INICIATIVAS!$R$7:$R$1000,$A5,BD_INICIATIVAS!$Y$7:$Y$1000,"<"&DATE(2026,3,1)) -> 0 | C5: =COUNTIFS(BD_INICIATIVAS!$R$7:$R$1000,$A5,BD_INICIATIVAS!$Y$7:$Y$1000,">="&DATE(2026,3,1),BD_INICIATIVAS!$Y$7:$Y$1000,"<"&DATE(2026,4,1)) -> 1 | D5: =COUNTIFS(BD_INICIATIVAS!$R$7:$R$1000,$A5,BD_INICIATIVAS!$Y$7:$Y$1000,">="&DATE(2026,4,1),BD_INICIATIVAS!$Y$7:$Y$1000,"<"&DATE(2026,5,1)) -> 0 | E5: =COUNTIFS(BD_INICIATIVAS!$R$7:$R$1000,$A5,BD_INICIATIVAS!$Y$7:$Y$1000,">="&DATE(2026,5,1),BD_INICIATIVAS!$Y$7:$Y$1000,"<"&DATE(2026,6,1)) -> 1 | F5: =COUNTIFS(BD_INICIATIVAS!$R$7:$R$1000,$A5,BD_INICIATIVAS!$Y$7:$Y$1000,">="&DATE(2026,6,1),BD_INICIATIVAS!$Y$7:$Y$1000,"<"&DATE(2026,7,1)) -> 1 | G5: =COUNTIFS(BD_INICIATIVAS!$R$7:$R$1000,$A5,BD_INICIATIVAS!$Y$7:$Y$1000,">="&DATE(2026,7,1),BD_INICIATIVAS!$Y$7:$Y$1000,"<"&DATE(2026,8,1)) -> 0 | H5: =COUNTIFS(BD_INICIATIVAS!$R$7:$R$1000,$A5,BD_INICIATIVAS!$Y$7:$Y$1000,">="&DATE(2026,8,1),BD_INICIATIVAS!$Y$7:$Y$1000,"<"&DATE(2026,9,1)) -> 3 | I5: =COUNTIFS(BD_INICIATIVAS!$R$7:$R$1000,$A5,BD_INICIATIVAS!$Y$7:$Y$1000,">="&DATE(2026,9,1),BD_INICIATIVAS!$Y$7:$Y$1000,"<"&DATE(2026,10,1)) -> 3 | J5: =COUNTIFS(BD_INICIATIVAS!$R$7:$R$1000,$A5,BD_INICIATIVAS!$Y$7:$Y$1000,">="&DATE(2026,10,1),BD_INICIATIVAS!$Y$7:$Y$1000,"<"&DATE(2026,11,1)) -> 1 | K5: =COUNTIFS(BD_INICIATIVAS!$R$7:$R$1000,$A5,BD_INICIATIVAS!$Y$7:$Y$1000,">="&DATE(2026,11,1),BD_INICIATIVAS!$Y$7:$Y$1000,"<"&DATE(2026,12,1)) -> 2 | L5: =COUNTIFS(BD_INICIATIVAS!$R$7:$R$1000,$A5,BD_INICIATIVAS!$Y$7:$Y$1000,">="&DATE(2026,12,1),BD_INICIATIVAS!$Y$7:$Y$1000,"<"&DATE(2027,1,1)) -> 1 | M5: =SUM(B5:L5) -> 13
A6: UTP Piura | B6: =COUNTIFS(BD_INICIATIVAS!$R$7:$R$1000,$A6,BD_INICIATIVAS!$Y$7:$Y$1000,"<"&DATE(2026,3,1)) -> 0 | C6: =COUNTIFS(BD_INICIATIVAS!$R$7:$R$1000,$A6,BD_INICIATIVAS!$Y$7:$Y$1000,">="&DATE(2026,3,1),BD_INICIATIVAS!$Y$7:$Y$1000,"<"&DATE(2026,4,1)) -> 2 | D6: =COUNTIFS(BD_INICIATIVAS!$R$7:$R$1000,$A6,BD_INICIATIVAS!$Y$7:$Y$1000,">="&DATE(2026,4,1),BD_INICIATIVAS!$Y$7:$Y$1000,"<"&DATE(2026,5,1)) -> 0 | E6: =COUNTIFS(BD_INICIATIVAS!$R$7:$R$1000,$A6,BD_INICIATIVAS!$Y$7:$Y$1000,">="&DATE(2026,5,1),BD_INICIATIVAS!$Y$7:$Y$1000,"<"&DATE(2026,6,1)) -> 2 | F6: =COUNTIFS(BD_INICIATIVAS!$R$7:$R$1000,$A6,BD_INICIATIVAS!$Y$7:$Y$1000,">="&DATE(2026,6,1),BD_INICIATIVAS!$Y$7:$Y$1000,"<"&DATE(2026,7,1)) -> 1 | G6: =COUNTIFS(BD_INICIATIVAS!$R$7:$R$1000,$A6,BD_INICIATIVAS!$Y$7:$Y$1000,">="&DATE(2026,7,1),BD_INICIATIVAS!$Y$7:$Y$1000,"<"&DATE(2026,8,1)) -> 0 | H6: =COUNTIFS(BD_INICIATIVAS!$R$7:$R$1000,$A6,BD_INICIATIVAS!$Y$7:$Y$1000,">="&DATE(2026,8,1),BD_INICIATIVAS!$Y$7:$Y$1000,"<"&DATE(2026,9,1)) -> 2 | I6: =COUNTIFS(BD_INICIATIVAS!$R$7:$R$1000,$A6,BD_INICIATIVAS!$Y$7:$Y$1000,">="&DATE(2026,9,1),BD_INICIATIVAS!$Y$7:$Y$1000,"<"&DATE(2026,10,1)) -> 0 | J6: =COUNTIFS(BD_INICIATIVAS!$R$7:$R$1000,$A6,BD_INICIATIVAS!$Y$7:$Y$1000,">="&DATE(2026,10,1),BD_INICIATIVAS!$Y$7:$Y$1000,"<"&DATE(2026,11,1)) -> 3 | K6: =COUNTIFS(BD_INICIATIVAS!$R$7:$R$1000,$A6,BD_INICIATIVAS!$Y$7:$Y$1000,">="&DATE(2026,11,1),BD_INICIATIVAS!$Y$7:$Y$1000,"<"&DATE(2026,12,1)) -> 3 | L6: =COUNTIFS(BD_INICIATIVAS!$R$7:$R$1000,$A6,BD_INICIATIVAS!$Y$7:$Y$1000,">="&DATE(2026,12,1),BD_INICIATIVAS!$Y$7:$Y$1000,"<"&DATE(2027,1,1)) -> 1 | M6: =SUM(B6:L6) -> 14
A7: UTP Trujillo | B7: =COUNTIFS(BD_INICIATIVAS!$R$7:$R$1000,$A7,BD_INICIATIVAS!$Y$7:$Y$1000,"<"&DATE(2026,3,1)) -> 0 | C7: =COUNTIFS(BD_INICIATIVAS!$R$7:$R$1000,$A7,BD_INICIATIVAS!$Y$7:$Y$1000,">="&DATE(2026,3,1),BD_INICIATIVAS!$Y$7:$Y$1000,"<"&DATE(2026,4,1)) -> 1 | D7: =COUNTIFS(BD_INICIATIVAS!$R$7:$R$1000,$A7,BD_INICIATIVAS!$Y$7:$Y$1000,">="&DATE(2026,4,1),BD_INICIATIVAS!$Y$7:$Y$1000,"<"&DATE(2026,5,1)) -> 0 | E7: =COUNTIFS(BD_INICIATIVAS!$R$7:$R$1000,$A7,BD_INICIATIVAS!$Y$7:$Y$1000,">="&DATE(2026,5,1),BD_INICIATIVAS!$Y$7:$Y$1000,"<"&DATE(2026,6,1)) -> 1 | F7: =COUNTIFS(BD_INICIATIVAS!$R$7:$R$1000,$A7,BD_INICIATIVAS!$Y$7:$Y$1000,">="&DATE(2026,6,1),BD_INICIATIVAS!$Y$7:$Y$1000,"<"&DATE(2026,7,1)) -> 2 | G7: =COUNTIFS(BD_INICIATIVAS!$R$7:$R$1000,$A7,BD_INICIATIVAS!$Y$7:$Y$1000,">="&DATE(2026,7,1),BD_INICIATIVAS!$Y$7:$Y$1000,"<"&DATE(2026,8,1)) -> 0 | H7: =COUNTIFS(BD_INICIATIVAS!$R$7:$R$1000,$A7,BD_INICIATIVAS!$Y$7:$Y$1000,">="&DATE(2026,8,1),BD_INICIATIVAS!$Y$7:$Y$1000,"<"&DATE(2026,9,1)) -> 3 | I7: =COUNTIFS(BD_INICIATIVAS!$R$7:$R$1000,$A7,BD_INICIATIVAS!$Y$7:$Y$1000,">="&DATE(2026,9,1),BD_INICIATIVAS!$Y$7:$Y$1000,"<"&DATE(2026,10,1)) -> 1 | J7: =COUNTIFS(BD_INICIATIVAS!$R$7:$R$1000,$A7,BD_INICIATIVAS!$Y$7:$Y$1000,">="&DATE(2026,10,1),BD_INICIATIVAS!$Y$7:$Y$1000,"<"&DATE(2026,11,1)) -> 1 | K7: =COUNTIFS(BD_INICIATIVAS!$R$7:$R$1000,$A7,BD_INICIATIVAS!$Y$7:$Y$1000,">="&DATE(2026,11,1),BD_INICIATIVAS!$Y$7:$Y$1000,"<"&DATE(2026,12,1)) -> 2 | L7: =COUNTIFS(BD_INICIATIVAS!$R$7:$R$1000,$A7,BD_INICIATIVAS!$Y$7:$Y$1000,">="&DATE(2026,12,1),BD_INICIATIVAS!$Y$7:$Y$1000,"<"&DATE(2027,1,1)) -> 1 | M7: =SUM(B7:L7) -> 12
A8: UTP Lima Norte | B8: =COUNTIFS(BD_INICIATIVAS!$R$7:$R$1000,$A8,BD_INICIATIVAS!$Y$7:$Y$1000,"<"&DATE(2026,3,1)) -> 0 | C8: =COUNTIFS(BD_INICIATIVAS!$R$7:$R$1000,$A8,BD_INICIATIVAS!$Y$7:$Y$1000,">="&DATE(2026,3,1),BD_INICIATIVAS!$Y$7:$Y$1000,"<"&DATE(2026,4,1)) -> 2 | D8: =COUNTIFS(BD_INICIATIVAS!$R$7:$R$1000,$A8,BD_INICIATIVAS!$Y$7:$Y$1000,">="&DATE(2026,4,1),BD_INICIATIVAS!$Y$7:$Y$1000,"<"&DATE(2026,5,1)) -> 0 | E8: =COUNTIFS(BD_INICIATIVAS!$R$7:$R$1000,$A8,BD_INICIATIVAS!$Y$7:$Y$1000,">="&DATE(2026,5,1),BD_INICIATIVAS!$Y$7:$Y$1000,"<"&DATE(2026,6,1)) -> 0 | F8: =COUNTIFS(BD_INICIATIVAS!$R$7:$R$1000,$A8,BD_INICIATIVAS!$Y$7:$Y$1000,">="&DATE(2026,6,1),BD_INICIATIVAS!$Y$7:$Y$1000,"<"&DATE(2026,7,1)) -> 1 | G8: =COUNTIFS(BD_INICIATIVAS!$R$7:$R$1000,$A8,BD_INICIATIVAS!$Y$7:$Y$1000,">="&DATE(2026,7,1),BD_INICIATIVAS!$Y$7:$Y$1000,"<"&DATE(2026,8,1)) -> 0 | H8: =COUNTIFS(BD_INICIATIVAS!$R$7:$R$1000,$A8,BD_INICIATIVAS!$Y$7:$Y$1000,">="&DATE(2026,8,1),BD_INICIATIVAS!$Y$7:$Y$1000,"<"&DATE(2026,9,1)) -> 1 | I8: =COUNTIFS(BD_INICIATIVAS!$R$7:$R$1000,$A8,BD_INICIATIVAS!$Y$7:$Y$1000,">="&DATE(2026,9,1),BD_INICIATIVAS!$Y$7:$Y$1000,"<"&DATE(2026,10,1)) -> 2 | J8: =COUNTIFS(BD_INICIATIVAS!$R$7:$R$1000,$A8,BD_INICIATIVAS!$Y$7:$Y$1000,">="&DATE(2026,10,1),BD_INICIATIVAS!$Y$7:$Y$1000,"<"&DATE(2026,11,1)) -> 2 | K8: =COUNTIFS(BD_INICIATIVAS!$R$7:$R$1000,$A8,BD_INICIATIVAS!$Y$7:$Y$1000,">="&DATE(2026,11,1),BD_INICIATIVAS!$Y$7:$Y$1000,"<"&DATE(2026,12,1)) -> 4 | L8: =COUNTIFS(BD_INICIATIVAS!$R$7:$R$1000,$A8,BD_INICIATIVAS!$Y$7:$Y$1000,">="&DATE(2026,12,1),BD_INICIATIVAS!$Y$7:$Y$1000,"<"&DATE(2027,1,1)) -> 1 | M8: =SUM(B8:L8) -> 13
A9: UTP Chimbote | B9: =COUNTIFS(BD_INICIATIVAS!$R$7:$R$1000,$A9,BD_INICIATIVAS!$Y$7:$Y$1000,"<"&DATE(2026,3,1)) -> 0 | C9: =COUNTIFS(BD_INICIATIVAS!$R$7:$R$1000,$A9,BD_INICIATIVAS!$Y$7:$Y$1000,">="&DATE(2026,3,1),BD_INICIATIVAS!$Y$7:$Y$1000,"<"&DATE(2026,4,1)) -> 1 | D9: =COUNTIFS(BD_INICIATIVAS!$R$7:$R$1000,$A9,BD_INICIATIVAS!$Y$7:$Y$1000,">="&DATE(2026,4,1),BD_INICIATIVAS!$Y$7:$Y$1000,"<"&DATE(2026,5,1)) -> 0 | E9: =COUNTIFS(BD_INICIATIVAS!$R$7:$R$1000,$A9,BD_INICIATIVAS!$Y$7:$Y$1000,">="&DATE(2026,5,1),BD_INICIATIVAS!$Y$7:$Y$1000,"<"&DATE(2026,6,1)) -> 1 | F9: =COUNTIFS(BD_INICIATIVAS!$R$7:$R$1000,$A9,BD_INICIATIVAS!$Y$7:$Y$1000,">="&DATE(2026,6,1),BD_INICIATIVAS!$Y$7:$Y$1000,"<"&DATE(2026,7,1)) -> 3 | G9: =COUNTIFS(BD_INICIATIVAS!$R$7:$R$1000,$A9,BD_INICIATIVAS!$Y$7:$Y$1000,">="&DATE(2026,7,1),BD_INICIATIVAS!$Y$7:$Y$1000,"<"&DATE(2026,8,1)) -> 0 | H9: =COUNTIFS(BD_INICIATIVAS!$R$7:$R$1000,$A9,BD_INICIATIVAS!$Y$7:$Y$1000,">="&DATE(2026,8,1),BD_INICIATIVAS!$Y$7:$Y$1000,"<"&DATE(2026,9,1)) -> 2 | I9: =COUNTIFS(BD_INICIATIVAS!$R$7:$R$1000,$A9,BD_INICIATIVAS!$Y$7:$Y$1000,">="&DATE(2026,9,1),BD_INICIATIVAS!$Y$7:$Y$1000,"<"&DATE(2026,10,1)) -> 0 | J9: =COUNTIFS(BD_INICIATIVAS!$R$7:$R$1000,$A9,BD_INICIATIVAS!$Y$7:$Y$1000,">="&DATE(2026,10,1),BD_INICIATIVAS!$Y$7:$Y$1000,"<"&DATE(2026,11,1)) -> 1 | K9: =COUNTIFS(BD_INICIATIVAS!$R$7:$R$1000,$A9,BD_INICIATIVAS!$Y$7:$Y$1000,">="&DATE(2026,11,1),BD_INICIATIVAS!$Y$7:$Y$1000,"<"&DATE(2026,12,1)) -> 2 | L9: =COUNTIFS(BD_INICIATIVAS!$R$7:$R$1000,$A9,BD_INICIATIVAS!$Y$7:$Y$1000,">="&DATE(2026,12,1),BD_INICIATIVAS!$Y$7:$Y$1000,"<"&DATE(2027,1,1)) -> 1 | M9: =SUM(B9:L9) -> 11
A10: UTP Lima Centro | B10: =COUNTIFS(BD_INICIATIVAS!$R$7:$R$1000,$A10,BD_INICIATIVAS!$Y$7:$Y$1000,"<"&DATE(2026,3,1)) -> 0 | C10: =COUNTIFS(BD_INICIATIVAS!$R$7:$R$1000,$A10,BD_INICIATIVAS!$Y$7:$Y$1000,">="&DATE(2026,3,1),BD_INICIATIVAS!$Y$7:$Y$1000,"<"&DATE(2026,4,1)) -> 7 | D10: =COUNTIFS(BD_INICIATIVAS!$R$7:$R$1000,$A10,BD_INICIATIVAS!$Y$7:$Y$1000,">="&DATE(2026,4,1),BD_INICIATIVAS!$Y$7:$Y$1000,"<"&DATE(2026,5,1)) -> 1 | E10: =COUNTIFS(BD_INICIATIVAS!$R$7:$R$1000,$A10,BD_INICIATIVAS!$Y$7:$Y$1000,">="&DATE(2026,5,1),BD_INICIATIVAS!$Y$7:$Y$1000,"<"&DATE(2026,6,1)) -> 6 | F10: =COUNTIFS(BD_INICIATIVAS!$R$7:$R$1000,$A10,BD_INICIATIVAS!$Y$7:$Y$1000,">="&DATE(2026,6,1),BD_INICIATIVAS!$Y$7:$Y$1000,"<"&DATE(2026,7,1)) -> 5 | G10: =COUNTIFS(BD_INICIATIVAS!$R$7:$R$1000,$A10,BD_INICIATIVAS!$Y$7:$Y$1000,">="&DATE(2026,7,1),BD_INICIATIVAS!$Y$7:$Y$1000,"<"&DATE(2026,8,1)) -> 3 | H10: =COUNTIFS(BD_INICIATIVAS!$R$7:$R$1000,$A10,BD_INICIATIVAS!$Y$7:$Y$1000,">="&DATE(2026,8,1),BD_INICIATIVAS!$Y$7:$Y$1000,"<"&DATE(2026,9,1)) -> 12 | I10: =COUNTIFS(BD_INICIATIVAS!$R$7:$R$1000,$A10,BD_INICIATIVAS!$Y$7:$Y$1000,">="&DATE(2026,9,1),BD_INICIATIVAS!$Y$7:$Y$1000,"<"&DATE(2026,10,1)) -> 5 | J10: =COUNTIFS(BD_INICIATIVAS!$R$7:$R$1000,$A10,BD_INICIATIVAS!$Y$7:$Y$1000,">="&DATE(2026,10,1),BD_INICIATIVAS!$Y$7:$Y$1000,"<"&DATE(2026,11,1)) -> 10 | K10: =COUNTIFS(BD_INICIATIVAS!$R$7:$R$1000,$A10,BD_INICIATIVAS!$Y$7:$Y$1000,">="&DATE(2026,11,1),BD_INICIATIVAS!$Y$7:$Y$1000,"<"&DATE(2026,12,1)) -> 10 | L10: =COUNTIFS(BD_INICIATIVAS!$R$7:$R$1000,$A10,BD_INICIATIVAS!$Y$7:$Y$1000,">="&DATE(2026,12,1),BD_INICIATIVAS!$Y$7:$Y$1000,"<"&DATE(2027,1,1)) -> 4 | M10: =SUM(B10:L10) -> 63
A11: UTP Lima Este | B11: =COUNTIFS(BD_INICIATIVAS!$R$7:$R$1000,$A11,BD_INICIATIVAS!$Y$7:$Y$1000,"<"&DATE(2026,3,1)) -> 0 | C11: =COUNTIFS(BD_INICIATIVAS!$R$7:$R$1000,$A11,BD_INICIATIVAS!$Y$7:$Y$1000,">="&DATE(2026,3,1),BD_INICIATIVAS!$Y$7:$Y$1000,"<"&DATE(2026,4,1)) -> 3 | D11: =COUNTIFS(BD_INICIATIVAS!$R$7:$R$1000,$A11,BD_INICIATIVAS!$Y$7:$Y$1000,">="&DATE(2026,4,1),BD_INICIATIVAS!$Y$7:$Y$1000,"<"&DATE(2026,5,1)) -> 0 | E11: =COUNTIFS(BD_INICIATIVAS!$R$7:$R$1000,$A11,BD_INICIATIVAS!$Y$7:$Y$1000,">="&DATE(2026,5,1),BD_INICIATIVAS!$Y$7:$Y$1000,"<"&DATE(2026,6,1)) -> 0 | F11: =COUNTIFS(BD_INICIATIVAS!$R$7:$R$1000,$A11,BD_INICIATIVAS!$Y$7:$Y$1000,">="&DATE(2026,6,1),BD_INICIATIVAS!$Y$7:$Y$1000,"<"&DATE(2026,7,1)) -> 1 | G11: =COUNTIFS(BD_INICIATIVAS!$R$7:$R$1000,$A11,BD_INICIATIVAS!$Y$7:$Y$1000,">="&DATE(2026,7,1),BD_INICIATIVAS!$Y$7:$Y$1000,"<"&DATE(2026,8,1)) -> 0 | H11: =COUNTIFS(BD_INICIATIVAS!$R$7:$R$1000,$A11,BD_INICIATIVAS!$Y$7:$Y$1000,">="&DATE(2026,8,1),BD_INICIATIVAS!$Y$7:$Y$1000,"<"&DATE(2026,9,1)) -> 3 | I11: =COUNTIFS(BD_INICIATIVAS!$R$7:$R$1000,$A11,BD_INICIATIVAS!$Y$7:$Y$1000,">="&DATE(2026,9,1),BD_INICIATIVAS!$Y$7:$Y$1000,"<"&DATE(2026,10,1)) -> 1 | J11: =COUNTIFS(BD_INICIATIVAS!$R$7:$R$1000,$A11,BD_INICIATIVAS!$Y$7:$Y$1000,">="&DATE(2026,10,1),BD_INICIATIVAS!$Y$7:$Y$1000,"<"&DATE(2026,11,1)) -> 1 | K11: =COUNTIFS(BD_INICIATIVAS!$R$7:$R$1000,$A11,BD_INICIATIVAS!$Y$7:$Y$1000,">="&DATE(2026,11,1),BD_INICIATIVAS!$Y$7:$Y$1000,"<"&DATE(2026,12,1)) -> 2 | L11: =COUNTIFS(BD_INICIATIVAS!$R$7:$R$1000,$A11,BD_INICIATIVAS!$Y$7:$Y$1000,">="&DATE(2026,12,1),BD_INICIATIVAS!$Y$7:$Y$1000,"<"&DATE(2027,1,1)) -> 1 | M11: =SUM(B11:L11) -> 12
A12: UTP Lima Sur | B12: =COUNTIFS(BD_INICIATIVAS!$R$7:$R$1000,$A12,BD_INICIATIVAS!$Y$7:$Y$1000,"<"&DATE(2026,3,1)) -> 0 | C12: =COUNTIFS(BD_INICIATIVAS!$R$7:$R$1000,$A12,BD_INICIATIVAS!$Y$7:$Y$1000,">="&DATE(2026,3,1),BD_INICIATIVAS!$Y$7:$Y$1000,"<"&DATE(2026,4,1)) -> 5 | D12: =COUNTIFS(BD_INICIATIVAS!$R$7:$R$1000,$A12,BD_INICIATIVAS!$Y$7:$Y$1000,">="&DATE(2026,4,1),BD_INICIATIVAS!$Y$7:$Y$1000,"<"&DATE(2026,5,1)) -> 1 | E12: =COUNTIFS(BD_INICIATIVAS!$R$7:$R$1000,$A12,BD_INICIATIVAS!$Y$7:$Y$1000,">="&DATE(2026,5,1),BD_INICIATIVAS!$Y$7:$Y$1000,"<"&DATE(2026,6,1)) -> 0 | F12: =COUNTIFS(BD_INICIATIVAS!$R$7:$R$1000,$A12,BD_INICIATIVAS!$Y$7:$Y$1000,">="&DATE(2026,6,1),BD_INICIATIVAS!$Y$7:$Y$1000,"<"&DATE(2026,7,1)) -> 1 | G12: =COUNTIFS(BD_INICIATIVAS!$R$7:$R$1000,$A12,BD_INICIATIVAS!$Y$7:$Y$1000,">="&DATE(2026,7,1),BD_INICIATIVAS!$Y$7:$Y$1000,"<"&DATE(2026,8,1)) -> 0 | H12: =COUNTIFS(BD_INICIATIVAS!$R$7:$R$1000,$A12,BD_INICIATIVAS!$Y$7:$Y$1000,">="&DATE(2026,8,1),BD_INICIATIVAS!$Y$7:$Y$1000,"<"&DATE(2026,9,1)) -> 2 | I12: =COUNTIFS(BD_INICIATIVAS!$R$7:$R$1000,$A12,BD_INICIATIVAS!$Y$7:$Y$1000,">="&DATE(2026,9,1),BD_INICIATIVAS!$Y$7:$Y$1000,"<"&DATE(2026,10,1)) -> 0 | J12: =COUNTIFS(BD_INICIATIVAS!$R$7:$R$1000,$A12,BD_INICIATIVAS!$Y$7:$Y$1000,">="&DATE(2026,10,1),BD_INICIATIVAS!$Y$7:$Y$1000,"<"&DATE(2026,11,1)) -> 2 | K12: =COUNTIFS(BD_INICIATIVAS!$R$7:$R$1000,$A12,BD_INICIATIVAS!$Y$7:$Y$1000,">="&DATE(2026,11,1),BD_INICIATIVAS!$Y$7:$Y$1000,"<"&DATE(2026,12,1)) -> 2 | L12: =COUNTIFS(BD_INICIATIVAS!$R$7:$R$1000,$A12,BD_INICIATIVAS!$Y$7:$Y$1000,">="&DATE(2026,12,1),BD_INICIATIVAS!$Y$7:$Y$1000,"<"&DATE(2027,1,1)) -> 1 | M12: =SUM(B12:L12) -> 14
A13: UTP Ica | B13: =COUNTIFS(BD_INICIATIVAS!$R$7:$R$1000,$A13,BD_INICIATIVAS!$Y$7:$Y$1000,"<"&DATE(2026,3,1)) -> 0 | C13: =COUNTIFS(BD_INICIATIVAS!$R$7:$R$1000,$A13,BD_INICIATIVAS!$Y$7:$Y$1000,">="&DATE(2026,3,1),BD_INICIATIVAS!$Y$7:$Y$1000,"<"&DATE(2026,4,1)) -> 0 | D13: =COUNTIFS(BD_INICIATIVAS!$R$7:$R$1000,$A13,BD_INICIATIVAS!$Y$7:$Y$1000,">="&DATE(2026,4,1),BD_INICIATIVAS!$Y$7:$Y$1000,"<"&DATE(2026,5,1)) -> 0 | E13: =COUNTIFS(BD_INICIATIVAS!$R$7:$R$1000,$A13,BD_INICIATIVAS!$Y$7:$Y$1000,">="&DATE(2026,5,1),BD_INICIATIVAS!$Y$7:$Y$1000,"<"&DATE(2026,6,1)) -> 2 | F13: =COUNTIFS(BD_INICIATIVAS!$R$7:$R$1000,$A13,BD_INICIATIVAS!$Y$7:$Y$1000,">="&DATE(2026,6,1),BD_INICIATIVAS!$Y$7:$Y$1000,"<"&DATE(2026,7,1)) -> 2 | G13: =COUNTIFS(BD_INICIATIVAS!$R$7:$R$1000,$A13,BD_INICIATIVAS!$Y$7:$Y$1000,">="&DATE(2026,7,1),BD_INICIATIVAS!$Y$7:$Y$1000,"<"&DATE(2026,8,1)) -> 0 | H13: =COUNTIFS(BD_INICIATIVAS!$R$7:$R$1000,$A13,BD_INICIATIVAS!$Y$7:$Y$1000,">="&DATE(2026,8,1),BD_INICIATIVAS!$Y$7:$Y$1000,"<"&DATE(2026,9,1)) -> 2 | I13: =COUNTIFS(BD_INICIATIVAS!$R$7:$R$1000,$A13,BD_INICIATIVAS!$Y$7:$Y$1000,">="&DATE(2026,9,1),BD_INICIATIVAS!$Y$7:$Y$1000,"<"&DATE(2026,10,1)) -> 1 | J13: =COUNTIFS(BD_INICIATIVAS!$R$7:$R$1000,$A13,BD_INICIATIVAS!$Y$7:$Y$1000,">="&DATE(2026,10,1),BD_INICIATIVAS!$Y$7:$Y$1000,"<"&DATE(2026,11,1)) -> 2 | K13: =COUNTIFS(BD_INICIATIVAS!$R$7:$R$1000,$A13,BD_INICIATIVAS!$Y$7:$Y$1000,">="&DATE(2026,11,1),BD_INICIATIVAS!$Y$7:$Y$1000,"<"&DATE(2026,12,1)) -> 2 | L13: =COUNTIFS(BD_INICIATIVAS!$R$7:$R$1000,$A13,BD_INICIATIVAS!$Y$7:$Y$1000,">="&DATE(2026,12,1),BD_INICIATIVAS!$Y$7:$Y$1000,"<"&DATE(2027,1,1)) -> 1 | M13: =SUM(B13:L13) -> 12
A14: UTP Chiclayo | B14: =COUNTIFS(BD_INICIATIVAS!$R$7:$R$1000,$A14,BD_INICIATIVAS!$Y$7:$Y$1000,"<"&DATE(2026,3,1)) -> 0 | C14: =COUNTIFS(BD_INICIATIVAS!$R$7:$R$1000,$A14,BD_INICIATIVAS!$Y$7:$Y$1000,">="&DATE(2026,3,1),BD_INICIATIVAS!$Y$7:$Y$1000,"<"&DATE(2026,4,1)) -> 3 | D14: =COUNTIFS(BD_INICIATIVAS!$R$7:$R$1000,$A14,BD_INICIATIVAS!$Y$7:$Y$1000,">="&DATE(2026,4,1),BD_INICIATIVAS!$Y$7:$Y$1000,"<"&DATE(2026,5,1)) -> 0 | E14: =COUNTIFS(BD_INICIATIVAS!$R$7:$R$1000,$A14,BD_INICIATIVAS!$Y$7:$Y$1000,">="&DATE(2026,5,1),BD_INICIATIVAS!$Y$7:$Y$1000,"<"&DATE(2026,6,1)) -> 1 | F14: =COUNTIFS(BD_INICIATIVAS!$R$7:$R$1000,$A14,BD_INICIATIVAS!$Y$7:$Y$1000,">="&DATE(2026,6,1),BD_INICIATIVAS!$Y$7:$Y$1000,"<"&DATE(2026,7,1)) -> 2 | G14: =COUNTIFS(BD_INICIATIVAS!$R$7:$R$1000,$A14,BD_INICIATIVAS!$Y$7:$Y$1000,">="&DATE(2026,7,1),BD_INICIATIVAS!$Y$7:$Y$1000,"<"&DATE(2026,8,1)) -> 0 | H14: =COUNTIFS(BD_INICIATIVAS!$R$7:$R$1000,$A14,BD_INICIATIVAS!$Y$7:$Y$1000,">="&DATE(2026,8,1),BD_INICIATIVAS!$Y$7:$Y$1000,"<"&DATE(2026,9,1)) -> 4 | I14: =COUNTIFS(BD_INICIATIVAS!$R$7:$R$1000,$A14,BD_INICIATIVAS!$Y$7:$Y$1000,">="&DATE(2026,9,1),BD_INICIATIVAS!$Y$7:$Y$1000,"<"&DATE(2026,10,1)) -> 1 | J14: =COUNTIFS(BD_INICIATIVAS!$R$7:$R$1000,$A14,BD_INICIATIVAS!$Y$7:$Y$1000,">="&DATE(2026,10,1),BD_INICIATIVAS!$Y$7:$Y$1000,"<"&DATE(2026,11,1)) -> 2 | K14: =COUNTIFS(BD_INICIATIVAS!$R$7:$R$1000,$A14,BD_INICIATIVAS!$Y$7:$Y$1000,">="&DATE(2026,11,1),BD_INICIATIVAS!$Y$7:$Y$1000,"<"&DATE(2026,12,1)) -> 4 | L14: =COUNTIFS(BD_INICIATIVAS!$R$7:$R$1000,$A14,BD_INICIATIVAS!$Y$7:$Y$1000,">="&DATE(2026,12,1),BD_INICIATIVAS!$Y$7:$Y$1000,"<"&DATE(2027,1,1)) -> 1 | M14: =SUM(B14:L14) -> 18
A15: UTP Huancayo | B15: =COUNTIFS(BD_INICIATIVAS!$R$7:$R$1000,$A15,BD_INICIATIVAS!$Y$7:$Y$1000,"<"&DATE(2026,3,1)) -> 0 | C15: =COUNTIFS(BD_INICIATIVAS!$R$7:$R$1000,$A15,BD_INICIATIVAS!$Y$7:$Y$1000,">="&DATE(2026,3,1),BD_INICIATIVAS!$Y$7:$Y$1000,"<"&DATE(2026,4,1)) -> 3 | D15: =COUNTIFS(BD_INICIATIVAS!$R$7:$R$1000,$A15,BD_INICIATIVAS!$Y$7:$Y$1000,">="&DATE(2026,4,1),BD_INICIATIVAS!$Y$7:$Y$1000,"<"&DATE(2026,5,1)) -> 0 | E15: =COUNTIFS(BD_INICIATIVAS!$R$7:$R$1000,$A15,BD_INICIATIVAS!$Y$7:$Y$1000,">="&DATE(2026,5,1),BD_INICIATIVAS!$Y$7:$Y$1000,"<"&DATE(2026,6,1)) -> 1 | F15: =COUNTIFS(BD_INICIATIVAS!$R$7:$R$1000,$A15,BD_INICIATIVAS!$Y$7:$Y$1000,">="&DATE(2026,6,1),BD_INICIATIVAS!$Y$7:$Y$1000,"<"&DATE(2026,7,1)) -> 3 | G15: =COUNTIFS(BD_INICIATIVAS!$R$7:$R$1000,$A15,BD_INICIATIVAS!$Y$7:$Y$1000,">="&DATE(2026,7,1),BD_INICIATIVAS!$Y$7:$Y$1000,"<"&DATE(2026,8,1)) -> 0 | H15: =COUNTIFS(BD_INICIATIVAS!$R$7:$R$1000,$A15,BD_INICIATIVAS!$Y$7:$Y$1000,">="&DATE(2026,8,1),BD_INICIATIVAS!$Y$7:$Y$1000,"<"&DATE(2026,9,1)) -> 1 | I15: =COUNTIFS(BD_INICIATIVAS!$R$7:$R$1000,$A15,BD_INICIATIVAS!$Y$7:$Y$1000,">="&DATE(2026,9,1),BD_INICIATIVAS!$Y$7:$Y$1000,"<"&DATE(2026,10,1)) -> 1 | J15: =COUNTIFS(BD_INICIATIVAS!$R$7:$R$1000,$A15,BD_INICIATIVAS!$Y$7:$Y$1000,">="&DATE(2026,10,1),BD_INICIATIVAS!$Y$7:$Y$1000,"<"&DATE(2026,11,1)) -> 1 | K15: =COUNTIFS(BD_INICIATIVAS!$R$7:$R$1000,$A15,BD_INICIATIVAS!$Y$7:$Y$1000,">="&DATE(2026,11,1),BD_INICIATIVAS!$Y$7:$Y$1000,"<"&DATE(2026,12,1)) -> 3 | L15: =COUNTIFS(BD_INICIATIVAS!$R$7:$R$1000,$A15,BD_INICIATIVAS!$Y$7:$Y$1000,">="&DATE(2026,12,1),BD_INICIATIVAS!$Y$7:$Y$1000,"<"&DATE(2027,1,1)) -> 1 | M15: =SUM(B15:L15) -> 14
A16: UTP Arequipa | B16: =COUNTIFS(BD_INICIATIVAS!$R$7:$R$1000,$A16,BD_INICIATIVAS!$Y$7:$Y$1000,"<"&DATE(2026,3,1)) -> 0 | C16: =COUNTIFS(BD_INICIATIVAS!$R$7:$R$1000,$A16,BD_INICIATIVAS!$Y$7:$Y$1000,">="&DATE(2026,3,1),BD_INICIATIVAS!$Y$7:$Y$1000,"<"&DATE(2026,4,1)) -> 0 | D16: =COUNTIFS(BD_INICIATIVAS!$R$7:$R$1000,$A16,BD_INICIATIVAS!$Y$7:$Y$1000,">="&DATE(2026,4,1),BD_INICIATIVAS!$Y$7:$Y$1000,"<"&DATE(2026,5,1)) -> 0 | E16: =COUNTIFS(BD_INICIATIVAS!$R$7:$R$1000,$A16,BD_INICIATIVAS!$Y$7:$Y$1000,">="&DATE(2026,5,1),BD_INICIATIVAS!$Y$7:$Y$1000,"<"&DATE(2026,6,1)) -> 1 | F16: =COUNTIFS(BD_INICIATIVAS!$R$7:$R$1000,$A16,BD_INICIATIVAS!$Y$7:$Y$1000,">="&DATE(2026,6,1),BD_INICIATIVAS!$Y$7:$Y$1000,"<"&DATE(2026,7,1)) -> 7 | G16: =COUNTIFS(BD_INICIATIVAS!$R$7:$R$1000,$A16,BD_INICIATIVAS!$Y$7:$Y$1000,">="&DATE(2026,7,1),BD_INICIATIVAS!$Y$7:$Y$1000,"<"&DATE(2026,8,1)) -> 0 | H16: =COUNTIFS(BD_INICIATIVAS!$R$7:$R$1000,$A16,BD_INICIATIVAS!$Y$7:$Y$1000,">="&DATE(2026,8,1),BD_INICIATIVAS!$Y$7:$Y$1000,"<"&DATE(2026,9,1)) -> 11 | I16: =COUNTIFS(BD_INICIATIVAS!$R$7:$R$1000,$A16,BD_INICIATIVAS!$Y$7:$Y$1000,">="&DATE(2026,9,1),BD_INICIATIVAS!$Y$7:$Y$1000,"<"&DATE(2026,10,1)) -> 0 | J16: =COUNTIFS(BD_INICIATIVAS!$R$7:$R$1000,$A16,BD_INICIATIVAS!$Y$7:$Y$1000,">="&DATE(2026,10,1),BD_INICIATIVAS!$Y$7:$Y$1000,"<"&DATE(2026,11,1)) -> 11 | K16: =COUNTIFS(BD_INICIATIVAS!$R$7:$R$1000,$A16,BD_INICIATIVAS!$Y$7:$Y$1000,">="&DATE(2026,11,1),BD_INICIATIVAS!$Y$7:$Y$1000,"<"&DATE(2026,12,1)) -> 8 | L16: =COUNTIFS(BD_INICIATIVAS!$R$7:$R$1000,$A16,BD_INICIATIVAS!$Y$7:$Y$1000,">="&DATE(2026,12,1),BD_INICIATIVAS!$Y$7:$Y$1000,"<"&DATE(2027,1,1)) -> 3 | M16: =SUM(B16:L16) -> 41
... A21: UTP EPG Salaverry | B21: =COUNTIFS(BD_INICIATIVAS!$R$7:$R$1000,$A21,BD_INICIATIVAS!$Y$7:$Y$1000,"<"&DATE(2026,3,1)) -> 0 | C21: =COUNTIFS(BD_INICIATIVAS!$R$7:$R$1000,$A21,BD_INICIATIVAS!$Y$7:$Y$1000,">="&DATE(2026,3,1),BD_INICIATIVAS!$Y$7:$Y$1000,"<"&DATE(2026,4,1)) -> 0 | D21: =COUNTIFS(BD_INICIATIVAS!$R$7:$R$1000,$A21,BD_INICIATIVAS!$Y$7:$Y$1000,">="&DATE(2026,4,1),BD_INICIATIVAS!$Y$7:$Y$1000,"<"&DATE(2026,5,1)) -> 0 | E21: =COUNTIFS(BD_INICIATIVAS!$R$7:$R$1000,$A21,BD_INICIATIVAS!$Y$7:$Y$1000,">="&DATE(2026,5,1),BD_INICIATIVAS!$Y$7:$Y$1000,"<"&DATE(2026,6,1)) -> 0 | F21: =COUNTIFS(BD_INICIATIVAS!$R$7:$R$1000,$A21,BD_INICIATIVAS!$Y$7:$Y$1000,">="&DATE(2026,6,1),BD_INICIATIVAS!$Y$7:$Y$1000,"<"&DATE(2026,7,1)) -> 0 | G21: =COUNTIFS(BD_INICIATIVAS!$R$7:$R$1000,$A21,BD_INICIATIVAS!$Y$7:$Y$1000,">="&DATE(2026,7,1),BD_INICIATIVAS!$Y$7:$Y$1000,"<"&DATE(2026,8,1)) -> 0 | H21: =COUNTIFS(BD_INICIATIVAS!$R$7:$R$1000,$A21,BD_INICIATIVAS!$Y$7:$Y$1000,">="&DATE(2026,8,1),BD_INICIATIVAS!$Y$7:$Y$1000,"<"&DATE(2026,9,1)) -> 1 | I21: =COUNTIFS(BD_INICIATIVAS!$R$7:$R$1000,$A21,BD_INICIATIVAS!$Y$7:$Y$1000,">="&DATE(2026,9,1),BD_INICIATIVAS!$Y$7:$Y$1000,"<"&DATE(2026,10,1)) -> 0 | J21: =COUNTIFS(BD_INICIATIVAS!$R$7:$R$1000,$A21,BD_INICIATIVAS!$Y$7:$Y$1000,">="&DATE(2026,10,1),BD_INICIATIVAS!$Y$7:$Y$1000,"<"&DATE(2026,11,1)) -> 0 | K21: =COUNTIFS(BD_INICIATIVAS!$R$7:$R$1000,$A21,BD_INICIATIVAS!$Y$7:$Y$1000,">="&DATE(2026,11,1),BD_INICIATIVAS!$Y$7:$Y$1000,"<"&DATE(2026,12,1)) -> 0 | L21: =COUNTIFS(BD_INICIATIVAS!$R$7:$R$1000,$A21,BD_INICIATIVAS!$Y$7:$Y$1000,">="&DATE(2026,12,1),BD_INICIATIVAS!$Y$7:$Y$1000,"<"&DATE(2027,1,1)) -> 0 | M21: =SUM(B21:L21) -> 1
A22: Total general | B22: =SUM(B5:B21) -> 0 | C22: =SUM(C5:C21) -> 28 | D22: =SUM(D5:D21) -> 2 | E22: =SUM(E5:E21) -> 19 | F22: =SUM(F5:F21) -> 30 | G22: =SUM(G5:G21) -> 3 | H22: =SUM(H5:H21) -> 47 | I22: =SUM(I5:I21) -> 15 | ... M22: =SUM(M5:M21) -> 254

Sheet LISTAS
A1: ESTADOS | B1: CAMPUS | C1: MESES
A2: EJECUTADO | B2: UTP SJL | C2: <1/03/2026
A3: EN PROCESO | B3: UTP Piura | C3: Mar
A4: PENDIENTE | B4: UTP Trujillo | C4: Abr
A5: CANCELADO | B5: UTP Lima Norte | C5: May
B6: UTP Chimbote | C6: Jun
B7: UTP Lima Centro | C7: Jul
B8: UTP Lima Este | C8: Ago
B9: UTP Lima Sur | C9: Set
B10: UTP Ica | C10: Oct
B11: UTP Chiclayo | C11: Nov
B12: UTP Huancayo | C12: Dic
B13: UTP Arequipa
B14: Corporativo - Natalio
B15: UTP Iquitos
B16: UTP Pucallpa
B17: UTP Tacna
B18: UTP EPG Salaverry

Sheet MEJORAS_PROGRAMACION
A1: campus | B1: fecha_inicio_texto | C1: fecha_fin_texto | D1: menor_01_03_2026 | E1: mar | F1: abr | G1: may | H1: jun | I1: jul | J1: ago | K1: set | L1: oct | M1: nov | N1: dic | O1: total
A2: UTP SJL | D2: 0 | E2: 1 | F2: 0 | G2: 1 | H2: 1 | I2: 0 | J2: 3 | K2: 3 | L2: 1 | M2: 2 | N2: 1 | O2: 13
A3: UTP Piura | D3: 0 | E3: 2 | F3: 0 | G3: 2 | H3: 1 | I3: 0 | J3: 2 | K3: 0 | L3: 3 | M3: 3 | N3: 1 | O3: 14
A4: UTP Trujillo | D4: 0 | E4: 1 | F4: 0 | G4: 1 | H4: 2 | I4: 0 | J4: 3 | K4: 1 | L4: 1 | M4: 2 | N4: 1 | O4: 12
A5: UTP Lima Norte | D5: 0 | E5: 2 | F5: 0 | G5: 0 | H5: 1 | I5: 0 | J5: 1 | K5: 2 | L5: 2 | M5: 4 | N5: 1 | O5: 13
A6: UTP Chimbote | D6: 0 | E6: 1 | F6: 0 | G6: 1 | H6: 3 | I6: 0 | J6: 2 | K6: 0 | L6: 1 | M6: 2 | N6: 1 | O6: 11
A7: UTP Lima Centro | D7: 0 | E7: 7 | F7: 1 | G7: 6 | H7: 5 | I7: 3 | J7: 12 | K7: 5 | L7: 10 | M7: 10 | N7: 4 | O7: 63
A8: UTP Lima Este | D8: 0 | E8: 3 | F8: 0 | G8: 0 | H8: 1 | I8: 0 | J8: 3 | K8: 1 | L8: 1 | M8: 2 | N8: 1 | O8: 12
A9: UTP Lima Sur | D9: 0 | E9: 5 | F9: 1 | G9: 0 | H9: 1 | I9: 0 | J9: 2 | K9: 0 | L9: 2 | M9: 2 | N9: 1 | O9: 14
A10: UTP Ica | D10: 0 | E10: 0 | F10: 0 | G10: 2 | H10: 2 | I10: 0 | J10: 2 | K10: 1 | L10: 2 | M10: 2 | N10: 1 | O10: 12
A11: UTP Chiclayo | D11: 0 | E11: 3 | F11: 0 | G11: 1 | H11: 2 | I11: 0 | J11: 4 | K11: 1 | L11: 2 | M11: 4 | N11: 1 | O11: 18
A12: UTP Huancayo | D12: 0 | E12: 3 | F12: 0 | G12: 1 | H12: 3 | I12: 0 | J12: 1 | K12: 1 | L12: 1 | M12: 3 | N12: 1 | O12: 14
A13: UTP Arequipa | D13: 0 | E13: 0 | F13: 0 | G13: 1 | H13: 7 | I13: 0 | J13: 11 | K13: 0 | L13: 11 | M13: 8 | N13: 3 | O13: 41
... A18: UTP EPG Salaverry | D18: 0 | E18: 0 | F18: 0 | G18: 0 | H18: 0 | I18: 0 | J18: 1 | K18: 0 | L18: 0 | M18: 0 | N18: 0 | O18: 1
